[
  {
    "round": 1,
    "target_concept": {
      "shape": "square",
      "color": "blue",
      "position": "bottom-right"
    },
    "symbol_message": "F2-G2-H4",
    "decoded_concept": {
      "shape": "triangle",
      "color": "blue",
      "position": "bottom-right"
    },
    "result": {
      "success": false,
      "attribute_scores": {
        "shape": false,
        "color": true,
        "position": true
      },
      "match_count": 2,
      "parse_error": false
    },
    "lexicon_size": 0,
    "cumulative_accuracy": 0.0,
    "speaker_raw_output": "I need to encode three properties: shape (square), color (blue), and position (bottom-right).\n\nLet me invent a systematic mapping:\n\n**Shape** \u2192 use F\n- F1 = circle, F2 = square, F3 = triangle, F4 = rectangle\n\n**Color** \u2192 use G\n- G1 = red, G2 = blue, G3 = green, G4 = yellow\n\n**Position** \u2192 use H\n- H1 = top-left, H2 = top-right, H3 = bottom-left, H4 = bottom-right\n\nSo:\n- shape = square \u2192 F2\n- color = blue \u2192 G2\n- position = bottom-right \u2192 H4\n\nF2-G2-H4",
    "listener_raw_output": "{\"shape\": \"triangle\", \"color\": \"blue\", \"position\": \"bottom-right\"}"
  },
  {
    "round": 2,
    "target_concept": {
      "shape": "star",
      "color": "green",
      "position": "top-right"
    },
    "symbol_message": "F3-G3-H2",
    "decoded_concept": {
      "shape": "square",
      "color": "green",
      "position": "top-right"
    },
    "result": {
      "success": false,
      "attribute_scores": {
        "shape": false,
        "color": true,
        "position": true
      },
      "match_count": 2,
      "parse_error": false
    },
    "lexicon_size": 0,
    "cumulative_accuracy": 0.0,
    "speaker_raw_output": "I need to encode three properties: shape (star), color (green), and position (top-right).\n\nLet me invent a systematic mapping from scratch:\n\n**Shape encoding (using F):**\n- F1 = circle\n- F2 = square\n- F3 = star\n- F4 = triangle\n\n**Color encoding (using G):**\n- G1 = red\n- G2 = blue\n- G3 = green\n- G4 = yellow\n\n**Position encoding (using H):**\n- H1 = top-left\n- H2 = top-right\n- H3 = bottom-left\n- H4 = bottom-right\n\nSo for \"star, green, top-right\":\n- Shape: star \u2192 F3\n- Color: green \u2192 G3\n- Position: top-right \u2192 H2\n\nF3-G3-H2",
    "listener_raw_output": "{\"shape\": \"square\", \"color\": \"green\", \"position\": \"top-right\"}"
  },
  {
    "round": 3,
    "target_concept": {
      "shape": "star",
      "color": "green",
      "position": "bottom-right"
    },
    "symbol_message": "F3-G3-H4",
    "decoded_concept": {
      "shape": "square",
      "color": "green",
      "position": "bottom-right"
    },
    "result": {
      "success": false,
      "attribute_scores": {
        "shape": false,
        "color": true,
        "position": true
      },
      "match_count": 2,
      "parse_error": false
    },
    "lexicon_size": 0,
    "cumulative_accuracy": 0.0,
    "speaker_raw_output": "I need to encode three attributes: shape (star), color (green), and position (bottom-right).\n\nLet me invent a systematic mapping:\n\n**Shape encoding** using F:\n- F1 = circle\n- F2 = square\n- F3 = star\n- F4 = triangle\n\n**Color encoding** using G:\n- G1 = red\n- G2 = blue\n- G3 = green\n- G4 = yellow\n\n**Position encoding** using H:\n- H1 = top-left\n- H2 = top-right\n- H3 = bottom-left\n- H4 = bottom-right\n\nSo for \"star, green, bottom-right\":\n- Shape: star = F3\n- Color: green = G3\n- Position: bottom-right = H4\n\nF3-G3-H4",
    "listener_raw_output": "{\"shape\": \"square\", \"color\": \"green\", \"position\": \"bottom-right\"}"
  },
  {
    "round": 4,
    "target_concept": {
      "shape": "triangle",
      "color": "yellow",
      "position": "top-right"
    },
    "symbol_message": "F3-G4-H2",
    "decoded_concept": {
      "shape": "square",
      "color": "yellow",
      "position": "top-right"
    },
    "result": {
      "success": false,
      "attribute_scores": {
        "shape": false,
        "color": true,
        "position": true
      },
      "match_count": 2,
      "parse_error": false
    },
    "lexicon_size": 0,
    "cumulative_accuracy": 0.0,
    "speaker_raw_output": "I need to encode three properties: shape (triangle), color (yellow), and position (top-right).\n\nSince the lexicon is empty, I'll invent mappings from scratch, trying to be systematic:\n\n**Shape encoding:**\n- Let F = shape dimension\n- Triangle = 3 sides \u2192 F3\n\n**Color encoding:**\n- Let G = color dimension\n- I'll assign colors to numbers: 1=red, 2=blue, 3=green, 4=yellow\n- Yellow \u2192 G4\n\n**Position encoding:**\n- Let H = position dimension\n- I'll think of positions on a 2x2 grid: 1=top-left, 2=top-right, 3=bottom-left, 4=bottom-right\n- Top-right \u2192 H2\n\nThis gives a compact 3-pair string encoding all three attributes.\n\nF3-G4-H2",
    "listener_raw_output": "{\"shape\": \"square\", \"color\": \"yellow\", \"position\": \"top-right\"}"
  },
  {
    "round": 5,
    "target_concept": {
      "shape": "star",
      "color": "blue",
      "position": "bottom-left"
    },
    "symbol_message": "F3-G2-H3",
    "decoded_concept": {
      "shape": "square",
      "color": "blue",
      "position": "bottom-left"
    },
    "result": {
      "success": false,
      "attribute_scores": {
        "shape": false,
        "color": true,
        "position": true
      },
      "match_count": 2,
      "parse_error": false
    },
    "lexicon_size": 0,
    "cumulative_accuracy": 0.0,
    "speaker_raw_output": "I need to encode three properties: shape (star), color (blue), and position (bottom-left).\n\nSince the lexicon is empty, I'll invent mappings from scratch:\n\n**Shape encoding:**\n- Let F = shape dimension\n- Star is a distinctive shape. I'll use F3 for star (arbitrary but systematic: 1=circle, 2=square, 3=star, 4=triangle)\n\n**Color encoding:**\n- Let G = color dimension\n- Blue: G2 (1=red, 2=blue, 3=green, 4=yellow)\n\n**Position encoding:**\n- Let H = position dimension\n- bottom-left: H3 (1=top-left, 2=top-right, 3=bottom-left, 4=bottom-right)\n\nThis gives a compact 3-pair encoding covering all three attributes.\n\nF3-G2-H3",
    "listener_raw_output": "{\"shape\": \"square\", \"color\": \"blue\", \"position\": \"bottom-left\"}"
  },
  {
    "round": 6,
    "target_concept": {
      "shape": "star",
      "color": "blue",
      "position": "top-left"
    },
    "symbol_message": "F1-G1-H1",
    "decoded_concept": {
      "shape": "circle",
      "color": "red",
      "position": "top-left"
    },
    "result": {
      "success": false,
      "attribute_scores": {
        "shape": false,
        "color": false,
        "position": true
      },
      "match_count": 1,
      "parse_error": false
    },
    "lexicon_size": 0,
    "cumulative_accuracy": 0.0,
    "speaker_raw_output": "I need to encode three properties: shape, color, and position. Since the lexicon is empty, I'll invent mappings from scratch.\n\n**Strategy:**\n\n- Use the **symbol letter** to represent the **property type**:\n  - F = shape\n  - G = color\n  - H = position\n\n- Use the **number** to represent the **value**:\n  - Shape: star=1, circle=2, square=3, triangle=4\n  - Color: blue=1, red=2, green=3, yellow=4\n  - Position: top-left=1, top-right=2, bottom-left=3, bottom-right=4\n\nSo:\n- shape=star \u2192 F1\n- color=blue \u2192 G1\n- position=top-left \u2192 H1\n\nF1-G1-H1",
    "listener_raw_output": "{\"shape\": \"circle\", \"color\": \"red\", \"position\": \"top-left\"}"
  },
  {
    "round": 7,
    "target_concept": {
      "shape": "circle",
      "color": "green",
      "position": "bottom-left"
    },
    "symbol_message": "F1-G2-H3",
    "decoded_concept": {
      "shape": "circle",
      "color": "blue",
      "position": "bottom-left"
    },
    "result": {
      "success": false,
      "attribute_scores": {
        "shape": true,
        "color": false,
        "position": true
      },
      "match_count": 2,
      "parse_error": false
    },
    "lexicon_size": 0,
    "cumulative_accuracy": 0.0,
    "speaker_raw_output": "I need to encode three features: shape (circle), color (green), and position (bottom-left).\n\nSince the lexicon is empty, I'll invent mappings:\n\n**Shape encoding:**\n- Let F = shape dimension\n- F1 = circle, F2 = square, F3 = triangle, F4 = other\n\n**Color encoding:**\n- Let G = color dimension\n- G1 = red, G2 = green, G3 = blue, G4 = yellow\n\n**Position encoding:**\n- Let H = position dimension\n- H1 = top-left, H2 = top-right, H3 = bottom-left, H4 = bottom-right\n\nSo:\n- circle \u2192 F1\n- green \u2192 G2\n- bottom-left \u2192 H3\n\nF1-G2-H3",
    "listener_raw_output": "{\"shape\": \"circle\", \"color\": \"blue\", \"position\": \"bottom-left\"}"
  },
  {
    "round": 8,
    "target_concept": {
      "shape": "star",
      "color": "red",
      "position": "bottom-right"
    },
    "symbol_message": "F1-G1-H4",
    "decoded_concept": {
      "shape": "circle",
      "color": "red",
      "position": "bottom-right"
    },
    "result": {
      "success": false,
      "attribute_scores": {
        "shape": false,
        "color": true,
        "position": true
      },
      "match_count": 2,
      "parse_error": false
    },
    "lexicon_size": 0,
    "cumulative_accuracy": 0.0,
    "speaker_raw_output": "I need to encode three attributes: shape (star), color (red), and position (bottom-right).\n\nSince the lexicon is empty, I'll invent mappings from scratch, trying to be systematic:\n\n**Shape encoding:**\n- I'll use the F symbol for shape\n- Star = F1 (star is the first shape I'm defining)\n\n**Color encoding:**\n- I'll use the G symbol for color\n- Red = G1 (red is the first color I'm defining)\n\n**Position encoding:**\n- I'll use the H symbol for position\n- I'll think of position as a grid: top=1, bottom=2 for vertical; left=1, right=2 for horizontal\n- But I need to combine bottom+right into one pair\n- bottom-right = H4 (thinking: top-left=1, top-right=2, bottom-left=3, bottom-right=4)\n\nSo the encoding is: F1-G1-H4\n\nF1-G1-H4",
    "listener_raw_output": "{\"shape\": \"circle\", \"color\": \"red\", \"position\": \"bottom-right\"}"
  },
  {
    "round": 9,
    "target_concept": {
      "shape": "star",
      "color": "red",
      "position": "bottom-right"
    },
    "symbol_message": "F4-G1-H4",
    "decoded_concept": {
      "shape": "star",
      "color": "red",
      "position": "bottom-right"
    },
    "result": {
      "success": true,
      "attribute_scores": {
        "shape": true,
        "color": true,
        "position": true
      },
      "match_count": 3,
      "parse_error": false
    },
    "lexicon_size": 4,
    "cumulative_accuracy": 0.1111111111111111,
    "speaker_raw_output": "I need to encode three features: shape (star), color (red), and position (bottom-right).\n\nSince this is a fresh lexicon, I'll invent mappings:\n\n**Shape encoding (using F):**\n- F1 = circle, F2 = square, F3 = triangle, F4 = star\n\u2192 Shape \"star\" = F4\n\n**Color encoding (using G):**\n- G1 = red, G2 = blue, G3 = green, G4 = yellow\n\u2192 Color \"red\" = G1\n\n**Position encoding (using H):**\n- H1 = top-left, H2 = top-right, H3 = bottom-left, H4 = bottom-right\n\u2192 Position \"bottom-right\" = H4\n\nSo the full encoding is F4-G1-H4\n\nF4-G1-H4",
    "listener_raw_output": "{\"shape\": \"star\", \"color\": \"red\", \"position\": \"bottom-right\"}"
  },
  {
    "round": 10,
    "target_concept": {
      "shape": "square",
      "color": "green",
      "position": "top-right"
    },
    "symbol_message": "F2-G2-H1",
    "decoded_concept": {
      "shape": "square",
      "color": "blue",
      "position": "top-left"
    },
    "result": {
      "success": false,
      "attribute_scores": {
        "shape": true,
        "color": false,
        "position": false
      },
      "match_count": 1,
      "parse_error": false
    },
    "lexicon_size": 4,
    "cumulative_accuracy": 0.1,
    "speaker_raw_output": "I need to encode: square, green, top-right.\n\nFrom the shared lexicon, I can see the pattern:\n- F codes seem to relate to shape (F4 = star)\n- G codes seem to relate to color (G1 = red)\n- H codes seem to relate to position (H4 = bottom-right)\n\nI need new mappings for:\n- square: F4 is star, so I'll use a different F number \u2192 F2 for square\n- green: G1 is red, so I'll use a different G number \u2192 G2 for green\n- top-right: H4 is bottom-right, so I'll use a different H number \u2192 H1 for top-right (thinking: top=1, bottom=4; right stays consistent)\n\nSo: F2 (square) - G2 (green) - H1 (top-right)\n\nF2-G2-H1",
    "listener_raw_output": "{\"shape\": \"square\", \"color\": \"blue\", \"position\": \"top-left\"}"
  },
  {
    "round": 11,
    "target_concept": {
      "shape": "triangle",
      "color": "yellow",
      "position": "bottom-right"
    },
    "symbol_message": "F1-G2-H4",
    "decoded_concept": {
      "shape": "circle",
      "color": "blue",
      "position": "bottom-right"
    },
    "result": {
      "success": false,
      "attribute_scores": {
        "shape": false,
        "color": false,
        "position": true
      },
      "match_count": 1,
      "parse_error": false
    },
    "lexicon_size": 4,
    "cumulative_accuracy": 0.09090909090909091,
    "speaker_raw_output": "I need to encode: triangle, yellow, bottom-right.\n\nFrom the shared lexicon:\n- H4 = bottom-right (established)\n- F4 = star, G1 = red (these are shape/color mappings)\n\nI need new symbols for:\n- triangle (shape) \u2192 I'll use F for shape category, F4=star, so I need a new number for triangle. F1 could be triangle (new mapping)\n- yellow (color) \u2192 G is color category, G1=red, so G2 could be yellow (new mapping)\n- bottom-right \u2192 H4 (established)\n\nSo: F1 (triangle) - G2 (yellow) - H4 (bottom-right)\n\nF1-G2-H4",
    "listener_raw_output": "{\"shape\": \"circle\", \"color\": \"blue\", \"position\": \"bottom-right\"}"
  },
  {
    "round": 12,
    "target_concept": {
      "shape": "triangle",
      "color": "green",
      "position": "bottom-right"
    },
    "symbol_message": "K1-G2-H4",
    "decoded_concept": {
      "shape": "circle",
      "color": "blue",
      "position": "bottom-right"
    },
    "result": {
      "success": false,
      "attribute_scores": {
        "shape": false,
        "color": false,
        "position": true
      },
      "match_count": 1,
      "parse_error": false
    },
    "lexicon_size": 4,
    "cumulative_accuracy": 0.08333333333333333,
    "speaker_raw_output": "I need to encode: triangle, green, bottom-right.\n\nFrom the shared lexicon:\n- H4 = bottom-right (established)\n- F4 = star, G1 = red (established, but I need triangle and green)\n\nI need new symbols for:\n- triangle: I'll use a new symbol. F is associated with star shape, so I'll use a different letter. Let me use \"K\" for triangle \u2192 K1\n- green: G1 is red, so I'll use a different number for green with G. G2 = green seems reasonable.\n- bottom-right: H4 (established)\n\nSo: K1-G2-H4\n\nK1-G2-H4",
    "listener_raw_output": "{\"shape\": \"circle\", \"color\": \"blue\", \"position\": \"bottom-right\"}"
  },
  {
    "round": 13,
    "target_concept": {
      "shape": "star",
      "color": "red",
      "position": "bottom-left"
    },
    "symbol_message": "F4-G1-H3",
    "decoded_concept": {
      "shape": "star",
      "color": "red",
      "position": "bottom-left"
    },
    "result": {
      "success": true,
      "attribute_scores": {
        "shape": true,
        "color": true,
        "position": true
      },
      "match_count": 3,
      "parse_error": false
    },
    "lexicon_size": 6,
    "cumulative_accuracy": 0.15384615384615385,
    "speaker_raw_output": "Looking at the target concept:\n- shape: \"star\" \u2192 F4 (from lexicon)\n- color: \"red\" \u2192 G1 (from lexicon)\n- position: \"bottom-left\" \u2192 need a new symbol. H4 is \"bottom-right\", so I'll use H3 for \"bottom-left\" (keeping H for vertical position \"bottom\", and using 3 instead of 4 to indicate left instead of right)\n\nF4-G1-H3",
    "listener_raw_output": "{\"shape\": \"star\", \"color\": \"red\", \"position\": \"bottom-left\"}"
  },
  {
    "round": 14,
    "target_concept": {
      "shape": "circle",
      "color": "green",
      "position": "top-right"
    },
    "symbol_message": "F1-G2-H2",
    "decoded_concept": {
      "shape": "circle",
      "color": "blue",
      "position": "top-right"
    },
    "result": {
      "success": false,
      "attribute_scores": {
        "shape": true,
        "color": false,
        "position": true
      },
      "match_count": 2,
      "parse_error": false
    },
    "lexicon_size": 6,
    "cumulative_accuracy": 0.14285714285714285,
    "speaker_raw_output": "I need to encode: circle, green, top-right.\n\nFrom the existing lexicon:\n- F = shape (F4 = star)\n- G = color (G1 = red)\n- H = position (H4 = bottom-right, H3 = bottom-left)\n\nI need new mappings for:\n- circle: F4 is star, so I'll use F1 for circle (a new shape value)\n- green: G1 is red, so I'll use G2 for green (a new color value)\n- top-right: H4 is bottom-right, H3 is bottom-left, so I'll use H2 for top-right (a new position value)\n\nThis follows the same F-G-H pattern for shape-color-position.\n\nF1-G2-H2",
    "listener_raw_output": "{\"shape\": \"circle\", \"color\": \"blue\", \"position\": \"top-right\"}"
  },
  {
    "round": 15,
    "target_concept": {
      "shape": "triangle",
      "color": "blue",
      "position": "bottom-left"
    },
    "symbol_message": "F1-G2-H3",
    "decoded_concept": {
      "shape": "circle",
      "color": "blue",
      "position": "bottom-left"
    },
    "result": {
      "success": false,
      "attribute_scores": {
        "shape": false,
        "color": true,
        "position": true
      },
      "match_count": 2,
      "parse_error": false
    },
    "lexicon_size": 6,
    "cumulative_accuracy": 0.13333333333333333,
    "speaker_raw_output": "Looking at the current lexicon:\n- F4 = star (shape)\n- G1 = red (color)\n- H3 = bottom-left (position)\n- H4 = bottom-right (position)\n\nI need to encode:\n- shape: triangle \u2192 F4 is star, so I need a new symbol for triangle. I'll use F1 for triangle (F seems to be the shape slot)\n- color: blue \u2192 G1 is red, so I need a new symbol for blue. I'll use G2 for blue (G seems to be the color slot)\n- position: bottom-left \u2192 H3 is already established as bottom-left \u2713\n\nSo my encoding: F1 (triangle) - G2 (blue) - H3 (bottom-left)\n\nF1-G2-H3",
    "listener_raw_output": "{\"shape\": \"circle\", \"color\": \"blue\", \"position\": \"bottom-left\"}"
  },
  {
    "round": 16,
    "target_concept": {
      "shape": "triangle",
      "color": "green",
      "position": "bottom-right"
    },
    "symbol_message": "F1-G2-H4",
    "decoded_concept": {
      "shape": "circle",
      "color": "blue",
      "position": "bottom-right"
    },
    "result": {
      "success": false,
      "attribute_scores": {
        "shape": false,
        "color": false,
        "position": true
      },
      "match_count": 1,
      "parse_error": false
    },
    "lexicon_size": 6,
    "cumulative_accuracy": 0.125,
    "speaker_raw_output": "Looking at the current lexicon:\n- F4 = star (shape)\n- G1 = red (color)\n- H4 = bottom-right (position)\n- H3 = bottom-left (position)\n\nI need to encode:\n- shape: triangle \u2192 F4 is \"star\", so I need a new symbol for triangle. I'll use F1 for triangle.\n- color: green \u2192 G1 is \"red\", so I need a new symbol for green. I'll use G2 for green.\n- position: bottom-right \u2192 H4 is already established for bottom-right \u2713\n\nSo my encoding: F1-G2-H4\n\nF1-G2-H4",
    "listener_raw_output": "{\"shape\": \"circle\", \"color\": \"blue\", \"position\": \"bottom-right\"}"
  },
  {
    "round": 17,
    "target_concept": {
      "shape": "triangle",
      "color": "green",
      "position": "bottom-right"
    },
    "symbol_message": "F2-G2-H4",
    "decoded_concept": {
      "shape": "square",
      "color": "blue",
      "position": "bottom-right"
    },
    "result": {
      "success": false,
      "attribute_scores": {
        "shape": false,
        "color": false,
        "position": true
      },
      "match_count": 1,
      "parse_error": false
    },
    "lexicon_size": 6,
    "cumulative_accuracy": 0.11764705882352941,
    "speaker_raw_output": "I need to encode: triangle, green, bottom-right.\n\nFrom the shared lexicon:\n- F = shape (F4 = star, so I need a new number for triangle)\n- G = color (G1 = red, so I need a new number for green)\n- H = position (H4 = bottom-right, H3 = bottom-left)\n\nMapping:\n- Triangle: F is shape, F4 is star. I'll use F2 for triangle (new mapping)\n- Green: G is color, G1 is red. I'll use G2 for green (new mapping)\n- Bottom-right: H4 (already established)\n\nSo the encoding is: F2-G2-H4\n\nF2-G2-H4",
    "listener_raw_output": "{\"shape\": \"square\", \"color\": \"blue\", \"position\": \"bottom-right\"}"
  },
  {
    "round": 18,
    "target_concept": {
      "shape": "square",
      "color": "green",
      "position": "top-right"
    },
    "symbol_message": "F1-G2-H2",
    "decoded_concept": {
      "shape": "circle",
      "color": "blue",
      "position": "top-right"
    },
    "result": {
      "success": false,
      "attribute_scores": {
        "shape": false,
        "color": false,
        "position": true
      },
      "match_count": 1,
      "parse_error": false
    },
    "lexicon_size": 6,
    "cumulative_accuracy": 0.1111111111111111,
    "speaker_raw_output": "Looking at the shared lexicon, I can see the established conventions:\n- F = shape (F4 = star)\n- G = color (G1 = red)\n- H = position (H4 = bottom-right, H3 = bottom-left)\n\nI need to encode:\n- shape: square \u2192 F is for shape, but F4 = star. I need a new value for square. I'll use F1 (since F4 is taken for star)\n- color: green \u2192 G is for color, but G1 = red. I'll use G2 for green\n- position: top-right \u2192 H is for position, H4 = bottom-right, H3 = bottom-left. I'll use H2 for top-right\n\nSo the encoding would be: F1-G2-H2\n\nF1-G2-H2",
    "listener_raw_output": "{\"shape\": \"circle\", \"color\": \"blue\", \"position\": \"top-right\"}"
  },
  {
    "round": 19,
    "target_concept": {
      "shape": "triangle",
      "color": "red",
      "position": "top-right"
    },
    "symbol_message": "F1-G1-H2",
    "decoded_concept": {
      "shape": "circle",
      "color": "red",
      "position": "top-right"
    },
    "result": {
      "success": false,
      "attribute_scores": {
        "shape": false,
        "color": true,
        "position": true
      },
      "match_count": 2,
      "parse_error": false
    },
    "lexicon_size": 6,
    "cumulative_accuracy": 0.10526315789473684,
    "speaker_raw_output": "Looking at the shared lexicon:\n- F4 = star (shape)\n- G1 = red (color)\n- H4 = bottom-right, H3 = bottom-left (positions)\n\nI need to encode:\n- shape: triangle \u2192 F4 is \"star\", so I need a new symbol for triangle. I'll use F1 for triangle (F seems to be shape, and 1 is unused for shape).\n- color: red \u2192 G1 (already established)\n- position: top-right \u2192 H4 is bottom-right, H3 is bottom-left. I need top-right. H seems to be position. I'll use H2 for top-right (extending the position mapping systematically).\n\nSo: F1 (triangle) - G1 (red) - H2 (top-right)\n\nF1-G1-H2",
    "listener_raw_output": "{\"shape\": \"circle\", \"color\": \"red\", \"position\": \"top-right\"}"
  },
  {
    "round": 20,
    "target_concept": {
      "shape": "square",
      "color": "yellow",
      "position": "top-left"
    },
    "symbol_message": "F1-G2-H1",
    "decoded_concept": {
      "shape": "circle",
      "color": "blue",
      "position": "top-left"
    },
    "result": {
      "success": false,
      "attribute_scores": {
        "shape": false,
        "color": false,
        "position": true
      },
      "match_count": 1,
      "parse_error": false
    },
    "lexicon_size": 6,
    "cumulative_accuracy": 0.1,
    "speaker_raw_output": "I need to encode: square, yellow, top-left.\n\nFrom the existing lexicon:\n- F = shape (F4 = star), so I need a new number for square. F4 is star, so I'll use F1 for square (new mapping).\n- G = color (G1 = red), so I need a new number for yellow. G1 is red, so I'll use G2 for yellow (new mapping).\n- H = position (H4 = bottom-right, H3 = bottom-left), so I need top-left. H3 is bottom-left, H4 is bottom-right. I'll use H1 for top-left (new mapping).\n\nSo: F1-G2-H1\n\nF1-G2-H1",
    "listener_raw_output": "{\"shape\": \"circle\", \"color\": \"blue\", \"position\": \"top-left\"}"
  },
  {
    "round": 21,
    "target_concept": {
      "shape": "square",
      "color": "green",
      "position": "top-right"
    },
    "symbol_message": "F1-G2-H2",
    "decoded_concept": {
      "shape": "circle",
      "color": "blue",
      "position": "top-right"
    },
    "result": {
      "success": false,
      "attribute_scores": {
        "shape": false,
        "color": false,
        "position": true
      },
      "match_count": 1,
      "parse_error": false
    },
    "lexicon_size": 6,
    "cumulative_accuracy": 0.09523809523809523,
    "speaker_raw_output": "I need to encode: square, green, top-right.\n\nFrom the shared lexicon, I can see the pattern:\n- F = shape (F4 = star)\n- G = color (G1 = red)\n- H = position (H4 = bottom-right, H3 = bottom-left)\n\nI need new mappings for:\n- square: F4 = star, so I'll use F1 for square (new)\n- green: G1 = red, so I'll use G2 for green (new)\n- top-right: H4 = bottom-right, H3 = bottom-left, so I'll use H2 for top-right (new)\n\nF1-G2-H2",
    "listener_raw_output": "{\"shape\": \"circle\", \"color\": \"blue\", \"position\": \"top-right\"}"
  },
  {
    "round": 22,
    "target_concept": {
      "shape": "square",
      "color": "yellow",
      "position": "top-right"
    },
    "symbol_message": "F1-G2-H2",
    "decoded_concept": {
      "shape": "circle",
      "color": "blue",
      "position": "top-right"
    },
    "result": {
      "success": false,
      "attribute_scores": {
        "shape": false,
        "color": false,
        "position": true
      },
      "match_count": 1,
      "parse_error": false
    },
    "lexicon_size": 6,
    "cumulative_accuracy": 0.09090909090909091,
    "speaker_raw_output": "I need to encode: square, yellow, top-right.\n\nFrom the existing lexicon:\n- F = shape (F4 = star)\n- G = color (G1 = red)\n- H = position (H4 = bottom-right, H3 = bottom-left)\n\nI need new mappings for:\n- square: F is shape, F4 = star, so I'll use a different number. F1 = square (new)\n- yellow: G1 = red, so I'll use G2 = yellow (new)\n- top-right: H4 = bottom-right, H3 = bottom-left, so H1 = top-right (new) or H2 = top-left. Let me use H2 = top-right (keeping some pattern... actually let me think: H3=bottom-left, H4=bottom-right, so H1=top-left, H2=top-right makes a consistent grid pattern)\n\nSo: F1 = square, G2 = yellow, H2 = top-right\n\nF1-G2-H2",
    "listener_raw_output": "{\"shape\": \"circle\", \"color\": \"blue\", \"position\": \"top-right\"}"
  },
  {
    "round": 23,
    "target_concept": {
      "shape": "circle",
      "color": "yellow",
      "position": "top-left"
    },
    "symbol_message": "F1-G2-H1",
    "decoded_concept": {
      "shape": "circle",
      "color": "blue",
      "position": "top-left"
    },
    "result": {
      "success": false,
      "attribute_scores": {
        "shape": true,
        "color": false,
        "position": true
      },
      "match_count": 2,
      "parse_error": false
    },
    "lexicon_size": 6,
    "cumulative_accuracy": 0.08695652173913043,
    "speaker_raw_output": "I need to encode: circle, yellow, top-left.\n\nFrom the existing lexicon:\n- F = shape (F4 = star, so I need a new number for circle, e.g., F1 = circle... but wait, ?F4 = star. Let me use F1 for circle since it's not yet assigned)\n- G = color (G1 = red, so I need a new number for yellow, e.g., G2 = yellow)\n- H = position (H4 = bottom-right, H3 = bottom-left, so I need top-left... H1 = top-left seems reasonable, H2 could be top-right)\n\nSo my encoding:\n- F1 = circle (new mapping)\n- G2 = yellow (new mapping)\n- H1 = top-left (new mapping)\n\nF1-G2-H1",
    "listener_raw_output": "{\"shape\": \"circle\", \"color\": \"blue\", \"position\": \"top-left\"}"
  },
  {
    "round": 24,
    "target_concept": {
      "shape": "square",
      "color": "green",
      "position": "top-left"
    },
    "symbol_message": "F1-G2-H1",
    "decoded_concept": {
      "shape": "circle",
      "color": "blue",
      "position": "top-left"
    },
    "result": {
      "success": false,
      "attribute_scores": {
        "shape": false,
        "color": false,
        "position": true
      },
      "match_count": 1,
      "parse_error": false
    },
    "lexicon_size": 6,
    "cumulative_accuracy": 0.08333333333333333,
    "speaker_raw_output": "I need to encode: square, green, top-left.\n\nFrom the existing lexicon:\n- F = shape (F4 = star, so I need a new number for square \u2192 F1, since F4 is star, let me use F2 for square... actually the lexicon shows ?F4 = star, so F4 is star. I'll use F1 for square)\n- G = color (G1 = red, so I need a new number for green \u2192 G2 for green)\n- H = position (H4 = bottom-right, H3 = bottom-left, so I need a new symbol/number for top-left \u2192 H1 for top-left, since top is the opposite of bottom and 1 could pair with 3/4 for top)\n\nSo my encoding:\n- F1 = square (new)\n- G2 = green (new)\n- H1 = top-left (new, H3=bottom-left, H4=bottom-right, H1=top-left makes sense)\n\nF1-G2-H1",
    "listener_raw_output": "{\"shape\": \"circle\", \"color\": \"blue\", \"position\": \"top-left\"}"
  },
  {
    "round": 25,
    "target_concept": {
      "shape": "star",
      "color": "red",
      "position": "top-left"
    },
    "symbol_message": "F4-G1-H1",
    "decoded_concept": {
      "shape": "star",
      "color": "red",
      "position": "top-left"
    },
    "result": {
      "success": true,
      "attribute_scores": {
        "shape": true,
        "color": true,
        "position": true
      },
      "match_count": 3,
      "parse_error": false
    },
    "lexicon_size": 8,
    "cumulative_accuracy": 0.12,
    "speaker_raw_output": "Looking at the shared lexicon:\n- F4 = star\n- G1 = red\n- H4 = bottom-right\n- H3 = bottom-left\n\nI need to encode \"top-left\". I can see H is used for position. H4 = bottom-right, H3 = bottom-left. I need a new value for top-left. \n\nFollowing a logical pattern:\n- H4 = bottom-right\n- H3 = bottom-left\n- H2 could = top-right\n- H1 could = top-left\n\nSo top-left = H1, which fits the pattern (lower numbers = top, higher = bottom; odd = left, even = right).\n\nF4-G1-H1",
    "listener_raw_output": "{\"shape\": \"star\", \"color\": \"red\", \"position\": \"top-left\"}"
  },
  {
    "round": 26,
    "target_concept": {
      "shape": "square",
      "color": "yellow",
      "position": "bottom-right"
    },
    "symbol_message": "F1-G2-H4",
    "decoded_concept": {
      "shape": "circle",
      "color": "blue",
      "position": "bottom-right"
    },
    "result": {
      "success": false,
      "attribute_scores": {
        "shape": false,
        "color": false,
        "position": true
      },
      "match_count": 1,
      "parse_error": false
    },
    "lexicon_size": 8,
    "cumulative_accuracy": 0.11538461538461539,
    "speaker_raw_output": "Looking at the shared lexicon:\n- F4 = star (shape)\n- G1 = red (color)\n- H4 = bottom-right (position)\n- H3 = bottom-left\n- H1 = top-left\n\nI need to encode:\n- shape: square \u2192 F is used for shape, F4 = star, so I need a new F code. I'll use F1 for square.\n- color: yellow \u2192 G is used for color, G1 = red, so I need a new G code. I'll use G2 for yellow.\n- position: bottom-right \u2192 H4 is already established for bottom-right.\n\nSo my encoding: F1-G2-H4\n\nF1-G2-H4",
    "listener_raw_output": "{\"shape\": \"circle\", \"color\": \"blue\", \"position\": \"bottom-right\"}"
  },
  {
    "round": 27,
    "target_concept": {
      "shape": "circle",
      "color": "red",
      "position": "top-right"
    },
    "symbol_message": "F1-G1-H2",
    "decoded_concept": {
      "shape": "circle",
      "color": "red",
      "position": "top-right"
    },
    "result": {
      "success": true,
      "attribute_scores": {
        "shape": true,
        "color": true,
        "position": true
      },
      "match_count": 3,
      "parse_error": false
    },
    "lexicon_size": 11,
    "cumulative_accuracy": 0.14814814814814814,
    "speaker_raw_output": "Looking at the shared lexicon:\n\n- `F4` = star (shape)\n- `G1` = red (color)\n- `H1` = top-left, `H3` = bottom-left, `H4` = bottom-right\n\nI need to encode:\n- **shape**: circle \u2192 no existing entry for circle. I'll use `F1` (since `F4` = star, a different F number for a different shape)\n- **color**: red \u2192 `G1` (established)\n- **position**: top-right \u2192 no existing entry. I have `H1`=top-left, `H3`=bottom-left, `H4`=bottom-right. Following the pattern, `H2` = top-right makes sense as the remaining position variant.\n\nSo: `F1-G1-H2`\n\nF1-G1-H2",
    "listener_raw_output": "{\"shape\": \"circle\", \"color\": \"red\", \"position\": \"top-right\"}"
  },
  {
    "round": 28,
    "target_concept": {
      "shape": "circle",
      "color": "red",
      "position": "top-right"
    },
    "symbol_message": "F1-G1-H2",
    "decoded_concept": {
      "shape": "circle",
      "color": "red",
      "position": "top-right"
    },
    "result": {
      "success": true,
      "attribute_scores": {
        "shape": true,
        "color": true,
        "position": true
      },
      "match_count": 3,
      "parse_error": false
    },
    "lexicon_size": 11,
    "cumulative_accuracy": 0.17857142857142858,
    "speaker_raw_output": "Looking at the target concept:\n- shape: circle \u2192 F1 (established in lexicon)\n- color: red \u2192 G1 (established in lexicon)\n- position: top-right \u2192 H2 (established in lexicon)\n\nThis exact combination \"F1-G1-H2\" maps perfectly to \"circle, red, top-right\" based on the existing lexicon entry.\n\nF1-G1-H2",
    "listener_raw_output": "{\"shape\": \"circle\", \"color\": \"red\", \"position\": \"top-right\"}"
  },
  {
    "round": 29,
    "target_concept": {
      "shape": "star",
      "color": "red",
      "position": "bottom-left"
    },
    "symbol_message": "F4-G1-H3",
    "decoded_concept": {
      "shape": "star",
      "color": "red",
      "position": "bottom-left"
    },
    "result": {
      "success": true,
      "attribute_scores": {
        "shape": true,
        "color": true,
        "position": true
      },
      "match_count": 3,
      "parse_error": false
    },
    "lexicon_size": 11,
    "cumulative_accuracy": 0.20689655172413793,
    "speaker_raw_output": "Looking at the target concept:\n- shape: \"star\" \u2192 F4 (established in lexicon)\n- color: \"red\" \u2192 G1 (established in lexicon)\n- position: \"bottom-left\" \u2192 H3 (established in lexicon)\n\nThis exact combination \"F4-G1-H3\" is already in the lexicon as \"star, red, bottom-left\". Perfect, I can use it directly.\n\nF4-G1-H3",
    "listener_raw_output": "{\"shape\": \"star\", \"color\": \"red\", \"position\": \"bottom-left\"}"
  },
  {
    "round": 30,
    "target_concept": {
      "shape": "triangle",
      "color": "yellow",
      "position": "bottom-right"
    },
    "symbol_message": "F2-G2-H4",
    "decoded_concept": {
      "shape": "triangle",
      "color": "blue",
      "position": "bottom-right"
    },
    "result": {
      "success": false,
      "attribute_scores": {
        "shape": true,
        "color": false,
        "position": true
      },
      "match_count": 2,
      "parse_error": false
    },
    "lexicon_size": 11,
    "cumulative_accuracy": 0.2,
    "speaker_raw_output": "Looking at the existing lexicon:\n- Shape is encoded with F: F1=circle, F4=star. Triangle has no mapping yet, so I'll assign F2=triangle (continuing the pattern).\n- Color is encoded with G: G1=red. Yellow has no mapping yet, so I'll assign G2=yellow.\n- Position is encoded with H: H1=top-left, H2=top-right, H3=bottom-left, H4=bottom-right. Bottom-right = H4.\n\nSo triangle=F2, yellow=G2, bottom-right=H4.\n\nF2-G2-H4",
    "listener_raw_output": "{\"shape\": \"triangle\", \"color\": \"blue\", \"position\": \"bottom-right\"}"
  },
  {
    "round": 31,
    "target_concept": {
      "shape": "triangle",
      "color": "red",
      "position": "bottom-right"
    },
    "symbol_message": "F2-G1-H4",
    "decoded_concept": {
      "shape": "triangle",
      "color": "red",
      "position": "bottom-right"
    },
    "result": {
      "success": true,
      "attribute_scores": {
        "shape": true,
        "color": true,
        "position": true
      },
      "match_count": 3,
      "parse_error": false
    },
    "lexicon_size": 13,
    "cumulative_accuracy": 0.22580645161290322,
    "speaker_raw_output": "Looking at the lexicon:\n- Shape: \"triangle\" has no existing entry. F1=circle, F4=star. I need a new symbol for triangle. I'll use F2 for triangle.\n- Color: G1=red \u2713\n- Position: H4=bottom-right \u2713\n\nSo the encoding is: F2 (triangle) + G1 (red) + H4 (bottom-right)\n\nF2-G1-H4",
    "listener_raw_output": "{\"shape\": \"triangle\", \"color\": \"red\", \"position\": \"bottom-right\"}"
  },
  {
    "round": 32,
    "target_concept": {
      "shape": "star",
      "color": "yellow",
      "position": "bottom-left"
    },
    "symbol_message": "F4-G2-H3",
    "decoded_concept": {
      "shape": "star",
      "color": "blue",
      "position": "bottom-left"
    },
    "result": {
      "success": false,
      "attribute_scores": {
        "shape": true,
        "color": false,
        "position": true
      },
      "match_count": 2,
      "parse_error": false
    },
    "lexicon_size": 13,
    "cumulative_accuracy": 0.21875,
    "speaker_raw_output": "Looking at the lexicon:\n- F4 = star \u2713\n- G1 = red (I need yellow \u2014 no entry yet, so I'll assign G2 = yellow)\n- H3 = bottom-left \u2713\n\nSo I'll encode: star=F4, yellow=G2 (new), bottom-left=H3\n\nF4-G2-H3",
    "listener_raw_output": "{\"shape\": \"star\", \"color\": \"blue\", \"position\": \"bottom-left\"}"
  },
  {
    "round": 33,
    "target_concept": {
      "shape": "circle",
      "color": "green",
      "position": "top-right"
    },
    "symbol_message": "F1-G2-H2",
    "decoded_concept": {
      "shape": "circle",
      "color": "blue",
      "position": "top-right"
    },
    "result": {
      "success": false,
      "attribute_scores": {
        "shape": true,
        "color": false,
        "position": true
      },
      "match_count": 2,
      "parse_error": false
    },
    "lexicon_size": 13,
    "cumulative_accuracy": 0.21212121212121213,
    "speaker_raw_output": "Looking at the lexicon:\n- F1 = circle \u2713\n- H2 = top-right \u2713\n- G1 = red, but I need green\n\nI need a new symbol for green. G1 is red, so I'll use G2 for green (a logical extension).\n\nThe encoding would be: F1 (circle) - G2 (green, new) - H2 (top-right)\n\nF1-G2-H2",
    "listener_raw_output": "{\"shape\": \"circle\", \"color\": \"blue\", \"position\": \"top-right\"}"
  },
  {
    "round": 34,
    "target_concept": {
      "shape": "star",
      "color": "yellow",
      "position": "top-left"
    },
    "symbol_message": "F4-G2-H1",
    "decoded_concept": {
      "shape": "star",
      "color": "blue",
      "position": "top-left"
    },
    "result": {
      "success": false,
      "attribute_scores": {
        "shape": true,
        "color": false,
        "position": true
      },
      "match_count": 2,
      "parse_error": false
    },
    "lexicon_size": 13,
    "cumulative_accuracy": 0.20588235294117646,
    "speaker_raw_output": "Looking at the lexicon:\n- F4 = star \u2713\n- G1 = red (I need yellow, which has no entry yet)\n- H1 = top-left \u2713\n\nFor yellow, I need a new color symbol. G1 is red, so I'll use G2 for yellow (a new convention).\n\nF4-G2-H1",
    "listener_raw_output": "{\"shape\": \"star\", \"color\": \"blue\", \"position\": \"top-left\"}"
  },
  {
    "round": 35,
    "target_concept": {
      "shape": "triangle",
      "color": "red",
      "position": "top-left"
    },
    "symbol_message": "F2-G1-H1",
    "decoded_concept": {
      "shape": "triangle",
      "color": "red",
      "position": "top-left"
    },
    "result": {
      "success": true,
      "attribute_scores": {
        "shape": true,
        "color": true,
        "position": true
      },
      "match_count": 3,
      "parse_error": false
    },
    "lexicon_size": 14,
    "cumulative_accuracy": 0.22857142857142856,
    "speaker_raw_output": "Looking at the target concept:\n- shape: triangle \u2192 F2 (established in lexicon)\n- color: red \u2192 G1 (established in lexicon)\n- position: top-left \u2192 H1 (established in lexicon)\n\nAll three components are already in the shared lexicon. I'll combine them consistently following the F-G-H pattern used throughout.\n\nF2-G1-H1",
    "listener_raw_output": "{\"shape\": \"triangle\", \"color\": \"red\", \"position\": \"top-left\"}"
  },
  {
    "round": 36,
    "target_concept": {
      "shape": "star",
      "color": "yellow",
      "position": "top-left"
    },
    "symbol_message": "F4-G2-H1",
    "decoded_concept": {
      "shape": "star",
      "color": "blue",
      "position": "top-left"
    },
    "result": {
      "success": false,
      "attribute_scores": {
        "shape": true,
        "color": false,
        "position": true
      },
      "match_count": 2,
      "parse_error": false
    },
    "lexicon_size": 14,
    "cumulative_accuracy": 0.2222222222222222,
    "speaker_raw_output": "Looking at the lexicon:\n- F4 = star \u2713\n- G1 = red, but I need yellow. No yellow entry yet, so I need to invent one. G2 could be yellow.\n- H1 = top-left \u2713\n\nSo I'll encode: star=F4, yellow=G2 (new), top-left=H1\n\nF4-G2-H1",
    "listener_raw_output": "{\"shape\": \"star\", \"color\": \"blue\", \"position\": \"top-left\"}"
  },
  {
    "round": 37,
    "target_concept": {
      "shape": "square",
      "color": "green",
      "position": "bottom-right"
    },
    "symbol_message": "F3-G2-H4",
    "decoded_concept": {
      "shape": "square",
      "color": "blue",
      "position": "bottom-right"
    },
    "result": {
      "success": false,
      "attribute_scores": {
        "shape": true,
        "color": false,
        "position": true
      },
      "match_count": 2,
      "parse_error": false
    },
    "lexicon_size": 14,
    "cumulative_accuracy": 0.21621621621621623,
    "speaker_raw_output": "Looking at the current lexicon:\n- Shape: F1=circle, F2=triangle, F4=star \u2192 I need a new symbol for \"square\". I'll use F3.\n- Color: G1=red \u2192 I need a new symbol for \"green\". I'll use G2.\n- Position: H1=top-left, H2=top-right, H3=bottom-left, H4=bottom-right \u2192 H4 already means bottom-right.\n\nSo I'll encode:\n- F3 = square (new)\n- G2 = green (new)\n- H4 = bottom-right (existing)\n\nF3-G2-H4",
    "listener_raw_output": "{\"shape\": \"square\", \"color\": \"blue\", \"position\": \"bottom-right\"}"
  },
  {
    "round": 38,
    "target_concept": {
      "shape": "square",
      "color": "red",
      "position": "top-right"
    },
    "symbol_message": "F3-G1-H2",
    "decoded_concept": {
      "shape": "square",
      "color": "red",
      "position": "top-right"
    },
    "result": {
      "success": true,
      "attribute_scores": {
        "shape": true,
        "color": true,
        "position": true
      },
      "match_count": 3,
      "parse_error": false
    },
    "lexicon_size": 16,
    "cumulative_accuracy": 0.23684210526315788,
    "speaker_raw_output": "Looking at the existing lexicon:\n- Shape encoding: F1=circle, F2=triangle, F4=star. I need a new symbol for \"square\". F3 would be a natural choice.\n- Color encoding: G1=red. \"Red\" is already established.\n- Position encoding: H1=top-left, H2=top-right, H3=bottom-left, H4=bottom-right. \"Top-right\" = H2, already established.\n\nSo for \"square, red, top-right\":\n- Shape \"square\" \u2192 F3 (new, fits the pattern)\n- Color \"red\" \u2192 G1 (established)\n- Position \"top-right\" \u2192 H2 (established)\n\nF3-G1-H2",
    "listener_raw_output": "{\"shape\": \"square\", \"color\": \"red\", \"position\": \"top-right\"}"
  },
  {
    "round": 39,
    "target_concept": {
      "shape": "star",
      "color": "blue",
      "position": "bottom-left"
    },
    "symbol_message": "F4-G2-H3",
    "decoded_concept": {
      "shape": "star",
      "color": "blue",
      "position": "bottom-left"
    },
    "result": {
      "success": true,
      "attribute_scores": {
        "shape": true,
        "color": true,
        "position": true
      },
      "match_count": 3,
      "parse_error": false
    },
    "lexicon_size": 18,
    "cumulative_accuracy": 0.2564102564102564,
    "speaker_raw_output": "I need to encode: star, blue, bottom-left\n\nFrom the lexicon:\n- F4 = star\n- H3 = bottom-left\n- G1 = red\n\nI need a new symbol for \"blue\". G1 is red, so I need a different G number for blue. I'll use G2 for blue.\n\nSo the encoding is: F4-G2-H3\n\nF4-G2-H3",
    "listener_raw_output": "{\"shape\": \"star\", \"color\": \"blue\", \"position\": \"bottom-left\"}"
  },
  {
    "round": 40,
    "target_concept": {
      "shape": "circle",
      "color": "blue",
      "position": "top-right"
    },
    "symbol_message": "F1-G2-H2",
    "decoded_concept": {
      "shape": "circle",
      "color": "blue",
      "position": "top-right"
    },
    "result": {
      "success": true,
      "attribute_scores": {
        "shape": true,
        "color": true,
        "position": true
      },
      "match_count": 3,
      "parse_error": false
    },
    "lexicon_size": 19,
    "cumulative_accuracy": 0.275,
    "speaker_raw_output": "Looking at the lexicon:\n- Circle = F1\n- Blue = G2\n- Top-right = H2\n\nAll three components are established in the lexicon. I can combine them directly.\n\nF1-G2-H2",
    "listener_raw_output": "{\"shape\": \"circle\", \"color\": \"blue\", \"position\": \"top-right\"}"
  },
  {
    "round": 41,
    "target_concept": {
      "shape": "square",
      "color": "red",
      "position": "top-left"
    },
    "symbol_message": "F3-G1-H1",
    "decoded_concept": {
      "shape": "square",
      "color": "red",
      "position": "top-left"
    },
    "result": {
      "success": true,
      "attribute_scores": {
        "shape": true,
        "color": true,
        "position": true
      },
      "match_count": 3,
      "parse_error": false
    },
    "lexicon_size": 20,
    "cumulative_accuracy": 0.2926829268292683,
    "speaker_raw_output": "Looking at the target concept: square, red, top-left\n\nFrom the shared lexicon:\n- ?F3 = \"square\" \u2192 F3\n- ?G1 = \"red\" \u2192 G1\n- ?H1 = \"top-left\" \u2192 H1\n\nThis follows the same pattern as other entries like \"F2-G1-H1\" for triangle, red, top-left and \"F4-G1-H1\" for star, red, top-left.\n\nF3-G1-H1",
    "listener_raw_output": "{\"shape\": \"square\", \"color\": \"red\", \"position\": \"top-left\"}"
  },
  {
    "round": 42,
    "target_concept": {
      "shape": "triangle",
      "color": "green",
      "position": "top-right"
    },
    "symbol_message": "F2-G3-H2",
    "decoded_concept": {
      "shape": "triangle",
      "color": "green",
      "position": "top-right"
    },
    "result": {
      "success": true,
      "attribute_scores": {
        "shape": true,
        "color": true,
        "position": true
      },
      "match_count": 3,
      "parse_error": false
    },
    "lexicon_size": 22,
    "cumulative_accuracy": 0.30952380952380953,
    "speaker_raw_output": "Looking at the lexicon:\n- F2 = triangle \u2713\n- G1 = red, G2 = blue \u2192 green has no entry yet, need a new symbol. G3 = green (new mapping)\n- H2 = top-right \u2713\n\nSo the encoding is: F2-G3-H2\n\nF2-G3-H2",
    "listener_raw_output": "{\"shape\": \"triangle\", \"color\": \"green\", \"position\": \"top-right\"}"
  },
  {
    "round": 43,
    "target_concept": {
      "shape": "triangle",
      "color": "red",
      "position": "top-left"
    },
    "symbol_message": "F2-G1-H1",
    "decoded_concept": {
      "shape": "triangle",
      "color": "red",
      "position": "top-left"
    },
    "result": {
      "success": true,
      "attribute_scores": {
        "shape": true,
        "color": true,
        "position": true
      },
      "match_count": 3,
      "parse_error": false
    },
    "lexicon_size": 22,
    "cumulative_accuracy": 0.32558139534883723,
    "speaker_raw_output": "Looking at the target concept:\n- shape: triangle \u2192 F2\n- color: red \u2192 G1\n- position: top-left \u2192 H1\n\nThis exact combination already exists in the lexicon: \"F2-G1-H1\": \"triangle, red, top-left\"\n\nF2-G1-H1",
    "listener_raw_output": "{\"shape\": \"triangle\", \"color\": \"red\", \"position\": \"top-left\"}"
  },
  {
    "round": 44,
    "target_concept": {
      "shape": "triangle",
      "color": "green",
      "position": "bottom-left"
    },
    "symbol_message": "F2-G3-H3",
    "decoded_concept": {
      "shape": "triangle",
      "color": "green",
      "position": "bottom-left"
    },
    "result": {
      "success": true,
      "attribute_scores": {
        "shape": true,
        "color": true,
        "position": true
      },
      "match_count": 3,
      "parse_error": false
    },
    "lexicon_size": 23,
    "cumulative_accuracy": 0.3409090909090909,
    "speaker_raw_output": "Looking at the lexicon:\n- Triangle = F2\n- Green = G3\n- Bottom-left = H3\n\nAll three components are established in the lexicon. I can combine them directly.\n\nF2-G3-H3",
    "listener_raw_output": "{\"shape\": \"triangle\", \"color\": \"green\", \"position\": \"bottom-left\"}"
  },
  {
    "round": 45,
    "target_concept": {
      "shape": "square",
      "color": "red",
      "position": "bottom-left"
    },
    "symbol_message": "F3-G1-H3",
    "decoded_concept": {
      "shape": "square",
      "color": "red",
      "position": "bottom-left"
    },
    "result": {
      "success": true,
      "attribute_scores": {
        "shape": true,
        "color": true,
        "position": true
      },
      "match_count": 3,
      "parse_error": false
    },
    "lexicon_size": 24,
    "cumulative_accuracy": 0.35555555555555557,
    "speaker_raw_output": "Looking at the lexicon:\n- F3 = square\n- G1 = red\n- H3 = bottom-left\n\nAll three components are already in the lexicon. I can combine them directly.\n\nF3-G1-H3",
    "listener_raw_output": "{\"shape\": \"square\", \"color\": \"red\", \"position\": \"bottom-left\"}"
  },
  {
    "round": 46,
    "target_concept": {
      "shape": "star",
      "color": "yellow",
      "position": "top-right"
    },
    "symbol_message": "F4-G4-H2",
    "decoded_concept": {
      "shape": "star",
      "color": "yellow",
      "position": "top-right"
    },
    "result": {
      "success": true,
      "attribute_scores": {
        "shape": true,
        "color": true,
        "position": true
      },
      "match_count": 3,
      "parse_error": false
    },
    "lexicon_size": 26,
    "cumulative_accuracy": 0.3695652173913043,
    "speaker_raw_output": "Looking at the lexicon:\n- F4 = star \u2713\n- G1 = red, G2 = blue, G3 = green \u2014 yellow has no entry yet, so I need a new symbol. G4 would be a logical choice for yellow.\n- H2 = top-right \u2713\n\nSo the encoding is: F4-G4-H2\n\nF4-G4-H2",
    "listener_raw_output": "{\"shape\": \"star\", \"color\": \"yellow\", \"position\": \"top-right\"}"
  },
  {
    "round": 47,
    "target_concept": {
      "shape": "square",
      "color": "green",
      "position": "bottom-left"
    },
    "symbol_message": "F3-G3-H3",
    "decoded_concept": {
      "shape": "square",
      "color": "green",
      "position": "bottom-left"
    },
    "result": {
      "success": true,
      "attribute_scores": {
        "shape": true,
        "color": true,
        "position": true
      },
      "match_count": 3,
      "parse_error": false
    },
    "lexicon_size": 27,
    "cumulative_accuracy": 0.3829787234042553,
    "speaker_raw_output": "Looking at the shared lexicon:\n- Square = F3\n- Green = G3\n- Bottom-left = H3\n\nAll three components have established mappings. I'll combine them following the same pattern used throughout the lexicon.\n\nF3-G3-H3",
    "listener_raw_output": "{\"shape\": \"square\", \"color\": \"green\", \"position\": \"bottom-left\"}"
  },
  {
    "round": 48,
    "target_concept": {
      "shape": "star",
      "color": "green",
      "position": "bottom-left"
    },
    "symbol_message": "F4-G3-H3",
    "decoded_concept": {
      "shape": "star",
      "color": "green",
      "position": "bottom-left"
    },
    "result": {
      "success": true,
      "attribute_scores": {
        "shape": true,
        "color": true,
        "position": true
      },
      "match_count": 3,
      "parse_error": false
    },
    "lexicon_size": 28,
    "cumulative_accuracy": 0.3958333333333333,
    "speaker_raw_output": "Looking at the lexicon:\n- F4 = star\n- G3 = green\n- H3 = bottom-left\n\nAll three components are already established in the lexicon. I can combine them directly.\n\nF4-G3-H3",
    "listener_raw_output": "{\"shape\": \"star\", \"color\": \"green\", \"position\": \"bottom-left\"}"
  },
  {
    "round": 49,
    "target_concept": {
      "shape": "circle",
      "color": "yellow",
      "position": "bottom-right"
    },
    "symbol_message": "F1-G4-H4",
    "decoded_concept": {
      "shape": "circle",
      "color": "yellow",
      "position": "bottom-right"
    },
    "result": {
      "success": true,
      "attribute_scores": {
        "shape": true,
        "color": true,
        "position": true
      },
      "match_count": 3,
      "parse_error": false
    },
    "lexicon_size": 29,
    "cumulative_accuracy": 0.40816326530612246,
    "speaker_raw_output": "Looking at the lexicon:\n- Circle = F1\n- Yellow = G4\n- Bottom-right = H4\n\nAll three components are established in the lexicon. I can combine them directly:\n\nF1-G4-H4",
    "listener_raw_output": "{\"shape\": \"circle\", \"color\": \"yellow\", \"position\": \"bottom-right\"}"
  },
  {
    "round": 50,
    "target_concept": {
      "shape": "star",
      "color": "yellow",
      "position": "top-left"
    },
    "symbol_message": "F4-G4-H1",
    "decoded_concept": {
      "shape": "star",
      "color": "yellow",
      "position": "top-left"
    },
    "result": {
      "success": true,
      "attribute_scores": {
        "shape": true,
        "color": true,
        "position": true
      },
      "match_count": 3,
      "parse_error": false
    },
    "lexicon_size": 30,
    "cumulative_accuracy": 0.42,
    "speaker_raw_output": "Looking at the shared lexicon:\n- F4 = star\n- G4 = yellow\n- H1 = top-left\n\nAll three components are already established in the lexicon. I can combine them directly.\n\nF4-G4-H1",
    "listener_raw_output": "{\"shape\": \"star\", \"color\": \"yellow\", \"position\": \"top-left\"}"
  },
  {
    "round": 51,
    "target_concept": {
      "shape": "star",
      "color": "blue",
      "position": "bottom-right"
    },
    "symbol_message": "F4-G2-H4",
    "decoded_concept": {
      "shape": "star",
      "color": "blue",
      "position": "bottom-right"
    },
    "result": {
      "success": true,
      "attribute_scores": {
        "shape": true,
        "color": true,
        "position": true
      },
      "match_count": 3,
      "parse_error": false
    },
    "lexicon_size": 31,
    "cumulative_accuracy": 0.43137254901960786,
    "speaker_raw_output": "Looking at the lexicon:\n- F4 = star\n- G2 = blue\n- H4 = bottom-right\n\nAll three components are already established in the shared lexicon. I'll combine them following the same pattern (shape-color-position).\n\nF4-G2-H4",
    "listener_raw_output": "{\"shape\": \"star\", \"color\": \"blue\", \"position\": \"bottom-right\"}"
  },
  {
    "round": 52,
    "target_concept": {
      "shape": "star",
      "color": "green",
      "position": "top-right"
    },
    "symbol_message": "F4-G3-H2",
    "decoded_concept": {
      "shape": "star",
      "color": "green",
      "position": "top-right"
    },
    "result": {
      "success": true,
      "attribute_scores": {
        "shape": true,
        "color": true,
        "position": true
      },
      "match_count": 3,
      "parse_error": false
    },
    "lexicon_size": 32,
    "cumulative_accuracy": 0.4423076923076923,
    "speaker_raw_output": "Looking at the lexicon:\n- F4 = star\n- G3 = green\n- H2 = top-right\n\nAll three components are already established in the lexicon. I'll combine them:\n\nF4-G3-H2",
    "listener_raw_output": "{\"shape\": \"star\", \"color\": \"green\", \"position\": \"top-right\"}"
  },
  {
    "round": 53,
    "target_concept": {
      "shape": "triangle",
      "color": "red",
      "position": "top-left"
    },
    "symbol_message": "F2-G1-H1",
    "decoded_concept": {
      "shape": "triangle",
      "color": "red",
      "position": "top-left"
    },
    "result": {
      "success": true,
      "attribute_scores": {
        "shape": true,
        "color": true,
        "position": true
      },
      "match_count": 3,
      "parse_error": false
    },
    "lexicon_size": 32,
    "cumulative_accuracy": 0.4528301886792453,
    "speaker_raw_output": "Looking at the lexicon:\n- Triangle = F2\n- Red = G1\n- Top-left = H1\n\nThis combination already exists in the lexicon: \"F2-G1-H1\" = \"triangle, red, top-left\" \u2713\n\nF2-G1-H1",
    "listener_raw_output": "{\"shape\": \"triangle\", \"color\": \"red\", \"position\": \"top-left\"}"
  },
  {
    "round": 54,
    "target_concept": {
      "shape": "circle",
      "color": "blue",
      "position": "bottom-right"
    },
    "symbol_message": "F1-G2-H4",
    "decoded_concept": {
      "shape": "circle",
      "color": "blue",
      "position": "bottom-right"
    },
    "result": {
      "success": true,
      "attribute_scores": {
        "shape": true,
        "color": true,
        "position": true
      },
      "match_count": 3,
      "parse_error": false
    },
    "lexicon_size": 33,
    "cumulative_accuracy": 0.46296296296296297,
    "speaker_raw_output": "Looking at the shared lexicon:\n- Circle = F1\n- Blue = G2\n- Bottom-right = H4\n\nAll three components are established in the lexicon. I'll combine them:\n\nF1-G2-H4",
    "listener_raw_output": "{\"shape\": \"circle\", \"color\": \"blue\", \"position\": \"bottom-right\"}"
  },
  {
    "round": 55,
    "target_concept": {
      "shape": "square",
      "color": "yellow",
      "position": "top-left"
    },
    "symbol_message": "F3-G4-H1",
    "decoded_concept": {
      "shape": "square",
      "color": "yellow",
      "position": "top-left"
    },
    "result": {
      "success": true,
      "attribute_scores": {
        "shape": true,
        "color": true,
        "position": true
      },
      "match_count": 3,
      "parse_error": false
    },
    "lexicon_size": 34,
    "cumulative_accuracy": 0.4727272727272727,
    "speaker_raw_output": "Looking at the shared lexicon:\n- F3 = square\n- G4 = yellow\n- H1 = top-left\n\nThese are all established conventions. I can combine them directly.\n\nF3-G4-H1",
    "listener_raw_output": "{\"shape\": \"square\", \"color\": \"yellow\", \"position\": \"top-left\"}"
  },
  {
    "round": 56,
    "target_concept": {
      "shape": "circle",
      "color": "green",
      "position": "bottom-right"
    },
    "symbol_message": "F1-G3-H4",
    "decoded_concept": {
      "shape": "circle",
      "color": "green",
      "position": "bottom-right"
    },
    "result": {
      "success": true,
      "attribute_scores": {
        "shape": true,
        "color": true,
        "position": true
      },
      "match_count": 3,
      "parse_error": false
    },
    "lexicon_size": 35,
    "cumulative_accuracy": 0.48214285714285715,
    "speaker_raw_output": "Looking at the lexicon:\n- Circle = F1\n- Green = G3\n- Bottom-right = H4\n\nAll three components are established in the lexicon. The combination F1-G3-H4 hasn't been used yet, but follows the consistent pattern of F(shape)-G(color)-H(position).\n\nF1-G3-H4",
    "listener_raw_output": "{\"shape\": \"circle\", \"color\": \"green\", \"position\": \"bottom-right\"}"
  },
  {
    "round": 57,
    "target_concept": {
      "shape": "square",
      "color": "green",
      "position": "bottom-right"
    },
    "symbol_message": "F3-G3-H4",
    "decoded_concept": {
      "shape": "square",
      "color": "green",
      "position": "bottom-right"
    },
    "result": {
      "success": true,
      "attribute_scores": {
        "shape": true,
        "color": true,
        "position": true
      },
      "match_count": 3,
      "parse_error": false
    },
    "lexicon_size": 36,
    "cumulative_accuracy": 0.49122807017543857,
    "speaker_raw_output": "Looking at the lexicon:\n- F3 = square\n- G3 = green\n- H4 = bottom-right\n\nThis follows the established pattern perfectly.\n\nF3-G3-H4",
    "listener_raw_output": "{\"shape\": \"square\", \"color\": \"green\", \"position\": \"bottom-right\"}"
  },
  {
    "round": 58,
    "target_concept": {
      "shape": "circle",
      "color": "red",
      "position": "top-left"
    },
    "symbol_message": "F1-G1-H1",
    "decoded_concept": {
      "shape": "circle",
      "color": "red",
      "position": "top-left"
    },
    "result": {
      "success": true,
      "attribute_scores": {
        "shape": true,
        "color": true,
        "position": true
      },
      "match_count": 3,
      "parse_error": false
    },
    "lexicon_size": 37,
    "cumulative_accuracy": 0.5,
    "speaker_raw_output": "Looking at the lexicon:\n- Circle = F1\n- Red = G1\n- Top-left = H1\n\nThis combination (circle, red, top-left) doesn't appear explicitly in the lexicon, but the components are all established. Following the consistent pattern used throughout:\n\nF1-G1-H1",
    "listener_raw_output": "{\"shape\": \"circle\", \"color\": \"red\", \"position\": \"top-left\"}"
  },
  {
    "round": 59,
    "target_concept": {
      "shape": "circle",
      "color": "yellow",
      "position": "top-left"
    },
    "symbol_message": "F1-G4-H1",
    "decoded_concept": {
      "shape": "circle",
      "color": "yellow",
      "position": "top-left"
    },
    "result": {
      "success": true,
      "attribute_scores": {
        "shape": true,
        "color": true,
        "position": true
      },
      "match_count": 3,
      "parse_error": false
    },
    "lexicon_size": 38,
    "cumulative_accuracy": 0.5084745762711864,
    "speaker_raw_output": "Looking at the lexicon:\n- Circle = F1\n- Yellow = G4\n- Top-left = H1\n\nThis combination hasn't been used before, but follows the established pattern perfectly.\n\nF1-G4-H1",
    "listener_raw_output": "{\"shape\": \"circle\", \"color\": \"yellow\", \"position\": \"top-left\"}"
  },
  {
    "round": 60,
    "target_concept": {
      "shape": "square",
      "color": "red",
      "position": "bottom-left"
    },
    "symbol_message": "F3-G1-H3",
    "decoded_concept": {
      "shape": "square",
      "color": "red",
      "position": "bottom-left"
    },
    "result": {
      "success": true,
      "attribute_scores": {
        "shape": true,
        "color": true,
        "position": true
      },
      "match_count": 3,
      "parse_error": false
    },
    "lexicon_size": 38,
    "cumulative_accuracy": 0.5166666666666667,
    "speaker_raw_output": "Looking at the lexicon:\n- F3 = square\n- G1 = red\n- H3 = bottom-left\n\nThis combination (F3-G1-H3) is already in the lexicon as \"square, red, bottom-left\". Perfect.\n\nF3-G1-H3",
    "listener_raw_output": "{\"shape\": \"square\", \"color\": \"red\", \"position\": \"bottom-left\"}"
  },
  {
    "round": 61,
    "target_concept": {
      "shape": "star",
      "color": "red",
      "position": "top-right"
    },
    "symbol_message": "F4-G1-H2",
    "decoded_concept": {
      "shape": "star",
      "color": "red",
      "position": "top-right"
    },
    "result": {
      "success": true,
      "attribute_scores": {
        "shape": true,
        "color": true,
        "position": true
      },
      "match_count": 3,
      "parse_error": false
    },
    "lexicon_size": 39,
    "cumulative_accuracy": 0.5245901639344263,
    "speaker_raw_output": "Looking at the target concept: star, red, top-right\n\nFrom the lexicon:\n- F4 = star\n- G1 = red\n- H2 = top-right\n\nThis combination (F4-G1-H2) doesn't exist yet in the lexicon, but all three components are well-established. I'll combine them following the same pattern used throughout.\n\nF4-G1-H2",
    "listener_raw_output": "{\"shape\": \"star\", \"color\": \"red\", \"position\": \"top-right\"}"
  },
  {
    "round": 62,
    "target_concept": {
      "shape": "square",
      "color": "green",
      "position": "bottom-right"
    },
    "symbol_message": "F3-G3-H4",
    "decoded_concept": {
      "shape": "square",
      "color": "green",
      "position": "bottom-right"
    },
    "result": {
      "success": true,
      "attribute_scores": {
        "shape": true,
        "color": true,
        "position": true
      },
      "match_count": 3,
      "parse_error": false
    },
    "lexicon_size": 39,
    "cumulative_accuracy": 0.532258064516129,
    "speaker_raw_output": "Looking at the target concept: square, green, bottom-right\n\nFrom the lexicon:\n- F3 = square\n- G3 = green\n- H4 = bottom-right\n\nThis combination F3-G3-H4 is already in the lexicon: \"square, green, bottom-right\" \u2713\n\nF3-G3-H4",
    "listener_raw_output": "{\"shape\": \"square\", \"color\": \"green\", \"position\": \"bottom-right\"}"
  },
  {
    "round": 63,
    "target_concept": {
      "shape": "star",
      "color": "blue",
      "position": "bottom-right"
    },
    "symbol_message": "F4-G2-H4",
    "decoded_concept": {
      "shape": "star",
      "color": "blue",
      "position": "bottom-right"
    },
    "result": {
      "success": true,
      "attribute_scores": {
        "shape": true,
        "color": true,
        "position": true
      },
      "match_count": 3,
      "parse_error": false
    },
    "lexicon_size": 39,
    "cumulative_accuracy": 0.5396825396825397,
    "speaker_raw_output": "Looking at the lexicon:\n- F4 = star\n- G2 = blue\n- H4 = bottom-right\n\nThis combination already exists in the lexicon: \"F4-G2-H4\" = \"star, blue, bottom-right\" \u2713\n\nF4-G2-H4",
    "listener_raw_output": "{\"shape\": \"star\", \"color\": \"blue\", \"position\": \"bottom-right\"}"
  },
  {
    "round": 64,
    "target_concept": {
      "shape": "circle",
      "color": "blue",
      "position": "bottom-right"
    },
    "symbol_message": "F1-G2-H4",
    "decoded_concept": {
      "shape": "circle",
      "color": "blue",
      "position": "bottom-right"
    },
    "result": {
      "success": true,
      "attribute_scores": {
        "shape": true,
        "color": true,
        "position": true
      },
      "match_count": 3,
      "parse_error": false
    },
    "lexicon_size": 39,
    "cumulative_accuracy": 0.546875,
    "speaker_raw_output": "Looking at the lexicon:\n- Circle = F1\n- Blue = G2\n- Bottom-right = H4\n\nThis combination (circle, blue, bottom-right) maps directly to F1-G2-H4, which is already in the lexicon.\n\nF1-G2-H4",
    "listener_raw_output": "{\"shape\": \"circle\", \"color\": \"blue\", \"position\": \"bottom-right\"}"
  },
  {
    "round": 65,
    "target_concept": {
      "shape": "circle",
      "color": "blue",
      "position": "bottom-left"
    },
    "symbol_message": "F1-G2-H3",
    "decoded_concept": {
      "shape": "circle",
      "color": "blue",
      "position": "bottom-left"
    },
    "result": {
      "success": true,
      "attribute_scores": {
        "shape": true,
        "color": true,
        "position": true
      },
      "match_count": 3,
      "parse_error": false
    },
    "lexicon_size": 40,
    "cumulative_accuracy": 0.5538461538461539,
    "speaker_raw_output": "Looking at the lexicon:\n- Circle = F1\n- Blue = G2\n- Bottom-left = H3\n\nThis combination hasn't been used yet, but follows the established pattern perfectly.\n\nF1-G2-H3",
    "listener_raw_output": "{\"shape\": \"circle\", \"color\": \"blue\", \"position\": \"bottom-left\"}"
  },
  {
    "round": 66,
    "target_concept": {
      "shape": "star",
      "color": "green",
      "position": "bottom-left"
    },
    "symbol_message": "F4-G3-H3",
    "decoded_concept": {
      "shape": "star",
      "color": "green",
      "position": "bottom-left"
    },
    "result": {
      "success": true,
      "attribute_scores": {
        "shape": true,
        "color": true,
        "position": true
      },
      "match_count": 3,
      "parse_error": false
    },
    "lexicon_size": 40,
    "cumulative_accuracy": 0.5606060606060606,
    "speaker_raw_output": "Looking at the lexicon:\n- F4 = star\n- G3 = green\n- H3 = bottom-left\n\nThis combination (F4-G3-H3) is already in the lexicon as \"star, green, bottom-left\". Perfect.\n\nF4-G3-H3",
    "listener_raw_output": "{\"shape\": \"star\", \"color\": \"green\", \"position\": \"bottom-left\"}"
  },
  {
    "round": 67,
    "target_concept": {
      "shape": "square",
      "color": "green",
      "position": "bottom-left"
    },
    "symbol_message": "F3-G3-H3",
    "decoded_concept": {
      "shape": "square",
      "color": "green",
      "position": "bottom-left"
    },
    "result": {
      "success": true,
      "attribute_scores": {
        "shape": true,
        "color": true,
        "position": true
      },
      "match_count": 3,
      "parse_error": false
    },
    "lexicon_size": 40,
    "cumulative_accuracy": 0.5671641791044776,
    "speaker_raw_output": "Looking at the target concept: square, green, bottom-left\n\nFrom the shared lexicon:\n- F3 = square\n- G3 = green\n- H3 = bottom-left\n\nThis combination F3-G3-H3 is already in the lexicon as \"square, green, bottom-left\". \n\nF3-G3-H3",
    "listener_raw_output": "{\"shape\": \"square\", \"color\": \"green\", \"position\": \"bottom-left\"}"
  },
  {
    "round": 68,
    "target_concept": {
      "shape": "circle",
      "color": "yellow",
      "position": "top-right"
    },
    "symbol_message": "F1-G4-H2",
    "decoded_concept": {
      "shape": "circle",
      "color": "yellow",
      "position": "top-right"
    },
    "result": {
      "success": true,
      "attribute_scores": {
        "shape": true,
        "color": true,
        "position": true
      },
      "match_count": 3,
      "parse_error": false
    },
    "lexicon_size": 41,
    "cumulative_accuracy": 0.5735294117647058,
    "speaker_raw_output": "Looking at the lexicon:\n- Circle = F1\n- Yellow = G4\n- Top-right = H2\n\nThis follows the established pattern perfectly.\n\nF1-G4-H2",
    "listener_raw_output": "{\"shape\": \"circle\", \"color\": \"yellow\", \"position\": \"top-right\"}"
  },
  {
    "round": 69,
    "target_concept": {
      "shape": "circle",
      "color": "blue",
      "position": "top-left"
    },
    "symbol_message": "F1-G2-H1",
    "decoded_concept": {
      "shape": "circle",
      "color": "blue",
      "position": "top-left"
    },
    "result": {
      "success": true,
      "attribute_scores": {
        "shape": true,
        "color": true,
        "position": true
      },
      "match_count": 3,
      "parse_error": false
    },
    "lexicon_size": 42,
    "cumulative_accuracy": 0.5797101449275363,
    "speaker_raw_output": "Looking at the lexicon:\n- Circle = F1\n- Blue = G2\n- Top-left = H1\n\nThis combination (F1-G2-H1) doesn't exist yet in the lexicon, but the components are all established. I'll combine them following the consistent pattern.\n\nF1-G2-H1",
    "listener_raw_output": "{\"shape\": \"circle\", \"color\": \"blue\", \"position\": \"top-left\"}"
  },
  {
    "round": 70,
    "target_concept": {
      "shape": "square",
      "color": "blue",
      "position": "top-left"
    },
    "symbol_message": "F3-G2-H1",
    "decoded_concept": {
      "shape": "square",
      "color": "blue",
      "position": "top-left"
    },
    "result": {
      "success": true,
      "attribute_scores": {
        "shape": true,
        "color": true,
        "position": true
      },
      "match_count": 3,
      "parse_error": false
    },
    "lexicon_size": 43,
    "cumulative_accuracy": 0.5857142857142857,
    "speaker_raw_output": "Looking at the lexicon:\n- F3 = square\n- G2 = blue\n- H1 = top-left\n\nThis combination hasn't been used yet, but follows the established pattern perfectly.\n\nF3-G2-H1",
    "listener_raw_output": "{\"shape\": \"square\", \"color\": \"blue\", \"position\": \"top-left\"}"
  },
  {
    "round": 71,
    "target_concept": {
      "shape": "circle",
      "color": "yellow",
      "position": "bottom-left"
    },
    "symbol_message": "F1-G4-H3",
    "decoded_concept": {
      "shape": "circle",
      "color": "yellow",
      "position": "bottom-left"
    },
    "result": {
      "success": true,
      "attribute_scores": {
        "shape": true,
        "color": true,
        "position": true
      },
      "match_count": 3,
      "parse_error": false
    },
    "lexicon_size": 44,
    "cumulative_accuracy": 0.5915492957746479,
    "speaker_raw_output": "Looking at the lexicon:\n- Circle = F1\n- Yellow = G4\n- Bottom-left = H3\n\nThis combination (F1-G4-H3) doesn't exist yet in the lexicon, but follows the established pattern perfectly.\n\nF1-G4-H3",
    "listener_raw_output": "{\"shape\": \"circle\", \"color\": \"yellow\", \"position\": \"bottom-left\"}"
  },
  {
    "round": 72,
    "target_concept": {
      "shape": "circle",
      "color": "blue",
      "position": "top-left"
    },
    "symbol_message": "F1-G2-H1",
    "decoded_concept": {
      "shape": "circle",
      "color": "blue",
      "position": "top-left"
    },
    "result": {
      "success": true,
      "attribute_scores": {
        "shape": true,
        "color": true,
        "position": true
      },
      "match_count": 3,
      "parse_error": false
    },
    "lexicon_size": 44,
    "cumulative_accuracy": 0.5972222222222222,
    "speaker_raw_output": "Looking at the lexicon, I can see:\n- F1 = circle\n- G2 = blue\n- H1 = top-left\n\nAnd indeed, \"F1-G2-H1\" is already in the lexicon as \"circle, blue, top-left\".\n\nF1-G2-H1",
    "listener_raw_output": "{\"shape\": \"circle\", \"color\": \"blue\", \"position\": \"top-left\"}"
  },
  {
    "round": 73,
    "target_concept": {
      "shape": "circle",
      "color": "yellow",
      "position": "top-left"
    },
    "symbol_message": "F1-G4-H1",
    "decoded_concept": {
      "shape": "circle",
      "color": "yellow",
      "position": "top-left"
    },
    "result": {
      "success": true,
      "attribute_scores": {
        "shape": true,
        "color": true,
        "position": true
      },
      "match_count": 3,
      "parse_error": false
    },
    "lexicon_size": 44,
    "cumulative_accuracy": 0.6027397260273972,
    "speaker_raw_output": "Looking at the lexicon:\n- Circle = F1\n- Yellow = G4\n- Top-left = H1\n\nThis combination \"F1-G4-H1\" is already in the lexicon as \"circle, yellow, top-left\". Perfect.\n\nF1-G4-H1",
    "listener_raw_output": "{\"shape\": \"circle\", \"color\": \"yellow\", \"position\": \"top-left\"}"
  },
  {
    "round": 74,
    "target_concept": {
      "shape": "square",
      "color": "green",
      "position": "bottom-right"
    },
    "symbol_message": "F3-G3-H4",
    "decoded_concept": {
      "shape": "square",
      "color": "green",
      "position": "bottom-right"
    },
    "result": {
      "success": true,
      "attribute_scores": {
        "shape": true,
        "color": true,
        "position": true
      },
      "match_count": 3,
      "parse_error": false
    },
    "lexicon_size": 44,
    "cumulative_accuracy": 0.6081081081081081,
    "speaker_raw_output": "Looking at the lexicon:\n- F3 = square\n- G3 = green\n- H4 = bottom-right\n\nThis combination F3-G3-H4 is already in the lexicon as \"square, green, bottom-right\". \n\nF3-G3-H4",
    "listener_raw_output": "{\"shape\": \"square\", \"color\": \"green\", \"position\": \"bottom-right\"}"
  },
  {
    "round": 75,
    "target_concept": {
      "shape": "circle",
      "color": "green",
      "position": "bottom-left"
    },
    "symbol_message": "F1-G3-H3",
    "decoded_concept": {
      "shape": "circle",
      "color": "green",
      "position": "bottom-left"
    },
    "result": {
      "success": true,
      "attribute_scores": {
        "shape": true,
        "color": true,
        "position": true
      },
      "match_count": 3,
      "parse_error": false
    },
    "lexicon_size": 45,
    "cumulative_accuracy": 0.6133333333333333,
    "speaker_raw_output": "Looking at the lexicon:\n- Circle = F1\n- Green = G3\n- Bottom-left = H3\n\nThis combination hasn't been used yet, but all components are established. I'll combine them:\n\nF1-G3-H3",
    "listener_raw_output": "{\"shape\": \"circle\", \"color\": \"green\", \"position\": \"bottom-left\"}"
  },
  {
    "round": 76,
    "target_concept": {
      "shape": "triangle",
      "color": "blue",
      "position": "bottom-right"
    },
    "symbol_message": "F2-G2-H4",
    "decoded_concept": {
      "shape": "triangle",
      "color": "blue",
      "position": "bottom-right"
    },
    "result": {
      "success": true,
      "attribute_scores": {
        "shape": true,
        "color": true,
        "position": true
      },
      "match_count": 3,
      "parse_error": false
    },
    "lexicon_size": 46,
    "cumulative_accuracy": 0.618421052631579,
    "speaker_raw_output": "Looking at the lexicon:\n- Triangle = F2\n- Blue = G2\n- Bottom-right = H4\n\nThis follows the established pattern perfectly.\n\nF2-G2-H4",
    "listener_raw_output": "{\"shape\": \"triangle\", \"color\": \"blue\", \"position\": \"bottom-right\"}"
  },
  {
    "round": 77,
    "target_concept": {
      "shape": "star",
      "color": "blue",
      "position": "bottom-right"
    },
    "symbol_message": "F4-G2-H4",
    "decoded_concept": {
      "shape": "star",
      "color": "blue",
      "position": "bottom-right"
    },
    "result": {
      "success": true,
      "attribute_scores": {
        "shape": true,
        "color": true,
        "position": true
      },
      "match_count": 3,
      "parse_error": false
    },
    "lexicon_size": 46,
    "cumulative_accuracy": 0.6233766233766234,
    "speaker_raw_output": "Looking at the lexicon:\n- F4 = star\n- G2 = blue\n- H4 = bottom-right\n\nThis combination \"F4-G2-H4\" is already in the lexicon as \"star, blue, bottom-right\". \n\nF4-G2-H4",
    "listener_raw_output": "{\"shape\": \"star\", \"color\": \"blue\", \"position\": \"bottom-right\"}"
  },
  {
    "round": 78,
    "target_concept": {
      "shape": "square",
      "color": "green",
      "position": "top-left"
    },
    "symbol_message": "F3-G3-H1",
    "decoded_concept": {
      "shape": "square",
      "color": "green",
      "position": "top-left"
    },
    "result": {
      "success": true,
      "attribute_scores": {
        "shape": true,
        "color": true,
        "position": true
      },
      "match_count": 3,
      "parse_error": false
    },
    "lexicon_size": 47,
    "cumulative_accuracy": 0.6282051282051282,
    "speaker_raw_output": "Looking at the lexicon:\n- F3 = square\n- G3 = green\n- H1 = top-left\n\nThis maps directly to F3-G3-H1.\n\nF3-G3-H1",
    "listener_raw_output": "{\"shape\": \"square\", \"color\": \"green\", \"position\": \"top-left\"}"
  },
  {
    "round": 79,
    "target_concept": {
      "shape": "square",
      "color": "red",
      "position": "bottom-left"
    },
    "symbol_message": "F3-G1-H3",
    "decoded_concept": {
      "shape": "square",
      "color": "red",
      "position": "bottom-left"
    },
    "result": {
      "success": true,
      "attribute_scores": {
        "shape": true,
        "color": true,
        "position": true
      },
      "match_count": 3,
      "parse_error": false
    },
    "lexicon_size": 47,
    "cumulative_accuracy": 0.6329113924050633,
    "speaker_raw_output": "Looking at the lexicon:\n- F3 = square\n- G1 = red\n- H3 = bottom-left\n\nThis combination \"F3-G1-H3\" is already in the lexicon as \"square, red, bottom-left\". Perfect.\n\nF3-G1-H3",
    "listener_raw_output": "{\"shape\": \"square\", \"color\": \"red\", \"position\": \"bottom-left\"}"
  },
  {
    "round": 80,
    "target_concept": {
      "shape": "triangle",
      "color": "yellow",
      "position": "top-right"
    },
    "symbol_message": "F2-G4-H2",
    "decoded_concept": {
      "shape": "triangle",
      "color": "yellow",
      "position": "top-right"
    },
    "result": {
      "success": true,
      "attribute_scores": {
        "shape": true,
        "color": true,
        "position": true
      },
      "match_count": 3,
      "parse_error": false
    },
    "lexicon_size": 48,
    "cumulative_accuracy": 0.6375,
    "speaker_raw_output": "Looking at the lexicon:\n- Triangle = F2\n- Yellow = G4\n- Top-right = H2\n\nThis follows the established pattern perfectly.\n\nF2-G4-H2",
    "listener_raw_output": "{\"shape\": \"triangle\", \"color\": \"yellow\", \"position\": \"top-right\"}"
  },
  {
    "round": 81,
    "target_concept": {
      "shape": "circle",
      "color": "green",
      "position": "bottom-right"
    },
    "symbol_message": "F1-G3-H4",
    "decoded_concept": {
      "shape": "circle",
      "color": "green",
      "position": "bottom-right"
    },
    "result": {
      "success": true,
      "attribute_scores": {
        "shape": true,
        "color": true,
        "position": true
      },
      "match_count": 3,
      "parse_error": false
    },
    "lexicon_size": 48,
    "cumulative_accuracy": 0.6419753086419753,
    "speaker_raw_output": "Looking at the lexicon:\n- Circle = F1\n- Green = G3\n- Bottom-right = H4\n\nThis combination (circle, green, bottom-right) maps to \"F1-G3-H4\" which is already in the lexicon.\n\nF1-G3-H4",
    "listener_raw_output": "{\"shape\": \"circle\", \"color\": \"green\", \"position\": \"bottom-right\"}"
  },
  {
    "round": 82,
    "target_concept": {
      "shape": "triangle",
      "color": "yellow",
      "position": "bottom-left"
    },
    "symbol_message": "F2-G4-H3",
    "decoded_concept": {
      "shape": "triangle",
      "color": "yellow",
      "position": "bottom-left"
    },
    "result": {
      "success": true,
      "attribute_scores": {
        "shape": true,
        "color": true,
        "position": true
      },
      "match_count": 3,
      "parse_error": false
    },
    "lexicon_size": 49,
    "cumulative_accuracy": 0.6463414634146342,
    "speaker_raw_output": "Looking at the lexicon:\n- Triangle = F2\n- Yellow = G4\n- Bottom-left = H3\n\nThis follows the established pattern perfectly: F2-G4-H3\n\nF2-G4-H3",
    "listener_raw_output": "{\"shape\": \"triangle\", \"color\": \"yellow\", \"position\": \"bottom-left\"}"
  },
  {
    "round": 83,
    "target_concept": {
      "shape": "circle",
      "color": "yellow",
      "position": "top-right"
    },
    "symbol_message": "F1-G4-H2",
    "decoded_concept": {
      "shape": "circle",
      "color": "yellow",
      "position": "top-right"
    },
    "result": {
      "success": true,
      "attribute_scores": {
        "shape": true,
        "color": true,
        "position": true
      },
      "match_count": 3,
      "parse_error": false
    },
    "lexicon_size": 49,
    "cumulative_accuracy": 0.6506024096385542,
    "speaker_raw_output": "Looking at the lexicon:\n- Circle = F1\n- Yellow = G4\n- Top-right = H2\n\nThis combination already exists in the lexicon: \"F1-G4-H2\" = \"circle, yellow, top-right\" \u2713\n\nF1-G4-H2",
    "listener_raw_output": "{\"shape\": \"circle\", \"color\": \"yellow\", \"position\": \"top-right\"}"
  },
  {
    "round": 84,
    "target_concept": {
      "shape": "star",
      "color": "red",
      "position": "bottom-right"
    },
    "symbol_message": "F4-G1-H4",
    "decoded_concept": {
      "shape": "star",
      "color": "red",
      "position": "bottom-right"
    },
    "result": {
      "success": true,
      "attribute_scores": {
        "shape": true,
        "color": true,
        "position": true
      },
      "match_count": 3,
      "parse_error": false
    },
    "lexicon_size": 49,
    "cumulative_accuracy": 0.6547619047619048,
    "speaker_raw_output": "Looking at the lexicon, I can see that:\n- F4 = star\n- G1 = red\n- H4 = bottom-right\n\nAnd in fact, \"F4-G1-H4\" is already in the lexicon as \"star, red, bottom-right\".\n\nF4-G1-H4",
    "listener_raw_output": "{\"shape\": \"star\", \"color\": \"red\", \"position\": \"bottom-right\"}"
  },
  {
    "round": 85,
    "target_concept": {
      "shape": "triangle",
      "color": "blue",
      "position": "bottom-right"
    },
    "symbol_message": "F2-G2-H4",
    "decoded_concept": {
      "shape": "triangle",
      "color": "blue",
      "position": "bottom-right"
    },
    "result": {
      "success": true,
      "attribute_scores": {
        "shape": true,
        "color": true,
        "position": true
      },
      "match_count": 3,
      "parse_error": false
    },
    "lexicon_size": 49,
    "cumulative_accuracy": 0.6588235294117647,
    "speaker_raw_output": "Looking at the lexicon:\n- Triangle = F2\n- Blue = G2\n- Bottom-right = H4\n\nThis combination (F2-G2-H4) is already in the lexicon as \"triangle, blue, bottom-right\". \u2713\n\nF2-G2-H4",
    "listener_raw_output": "{\"shape\": \"triangle\", \"color\": \"blue\", \"position\": \"bottom-right\"}"
  },
  {
    "round": 86,
    "target_concept": {
      "shape": "circle",
      "color": "green",
      "position": "bottom-left"
    },
    "symbol_message": "F1-G3-H3",
    "decoded_concept": {
      "shape": "circle",
      "color": "green",
      "position": "bottom-left"
    },
    "result": {
      "success": true,
      "attribute_scores": {
        "shape": true,
        "color": true,
        "position": true
      },
      "match_count": 3,
      "parse_error": false
    },
    "lexicon_size": 49,
    "cumulative_accuracy": 0.6627906976744186,
    "speaker_raw_output": "Looking at the lexicon:\n- Circle = F1\n- Green = G3\n- Bottom-left = H3\n\nThis combination (circle, green, bottom-left) maps to \"F1-G3-H3\" which is already in the lexicon.\n\nF1-G3-H3",
    "listener_raw_output": "{\"shape\": \"circle\", \"color\": \"green\", \"position\": \"bottom-left\"}"
  },
  {
    "round": 87,
    "target_concept": {
      "shape": "square",
      "color": "green",
      "position": "bottom-right"
    },
    "symbol_message": "F3-G3-H4",
    "decoded_concept": {
      "shape": "square",
      "color": "green",
      "position": "bottom-right"
    },
    "result": {
      "success": true,
      "attribute_scores": {
        "shape": true,
        "color": true,
        "position": true
      },
      "match_count": 3,
      "parse_error": false
    },
    "lexicon_size": 49,
    "cumulative_accuracy": 0.6666666666666666,
    "speaker_raw_output": "Looking at the lexicon:\n- F3 = square\n- G3 = green\n- H4 = bottom-right\n\nThis combination (F3-G3-H4) is already in the lexicon as \"square, green, bottom-right\". \n\nF3-G3-H4",
    "listener_raw_output": "{\"shape\": \"square\", \"color\": \"green\", \"position\": \"bottom-right\"}"
  },
  {
    "round": 88,
    "target_concept": {
      "shape": "triangle",
      "color": "red",
      "position": "bottom-right"
    },
    "symbol_message": "F2-G1-H4",
    "decoded_concept": {
      "shape": "triangle",
      "color": "red",
      "position": "bottom-right"
    },
    "result": {
      "success": true,
      "attribute_scores": {
        "shape": true,
        "color": true,
        "position": true
      },
      "match_count": 3,
      "parse_error": false
    },
    "lexicon_size": 49,
    "cumulative_accuracy": 0.6704545454545454,
    "speaker_raw_output": "Looking at the lexicon:\n- Triangle = F2\n- Red = G1\n- Bottom-right = H4\n\nThis combination follows the established pattern perfectly: F2-G1-H4\n\nF2-G1-H4",
    "listener_raw_output": "{\"shape\": \"triangle\", \"color\": \"red\", \"position\": \"bottom-right\"}"
  },
  {
    "round": 89,
    "target_concept": {
      "shape": "star",
      "color": "red",
      "position": "top-right"
    },
    "symbol_message": "F4-G1-H2",
    "decoded_concept": {
      "shape": "star",
      "color": "red",
      "position": "top-right"
    },
    "result": {
      "success": true,
      "attribute_scores": {
        "shape": true,
        "color": true,
        "position": true
      },
      "match_count": 3,
      "parse_error": false
    },
    "lexicon_size": 49,
    "cumulative_accuracy": 0.6741573033707865,
    "speaker_raw_output": "Looking at the lexicon, I can see the established conventions:\n- F4 = star\n- G1 = red\n- H2 = top-right\n\nThe combination \"star, red, top-right\" maps directly to F4-G1-H2, which is already in the lexicon.\n\nF4-G1-H2",
    "listener_raw_output": "{\"shape\": \"star\", \"color\": \"red\", \"position\": \"top-right\"}"
  },
  {
    "round": 90,
    "target_concept": {
      "shape": "circle",
      "color": "blue",
      "position": "bottom-left"
    },
    "symbol_message": "F1-G2-H3",
    "decoded_concept": {
      "shape": "circle",
      "color": "blue",
      "position": "bottom-left"
    },
    "result": {
      "success": true,
      "attribute_scores": {
        "shape": true,
        "color": true,
        "position": true
      },
      "match_count": 3,
      "parse_error": false
    },
    "lexicon_size": 49,
    "cumulative_accuracy": 0.6777777777777778,
    "speaker_raw_output": "Looking at the lexicon:\n- Circle = F1\n- Blue = G2\n- Bottom-left = H3\n\nThis combination exists in the lexicon as \"F1-G2-H3\" = \"circle, blue, bottom-left\" \u2713\n\nF1-G2-H3",
    "listener_raw_output": "{\"shape\": \"circle\", \"color\": \"blue\", \"position\": \"bottom-left\"}"
  },
  {
    "round": 91,
    "target_concept": {
      "shape": "circle",
      "color": "yellow",
      "position": "top-right"
    },
    "symbol_message": "F1-G4-H2",
    "decoded_concept": {
      "shape": "circle",
      "color": "yellow",
      "position": "top-right"
    },
    "result": {
      "success": true,
      "attribute_scores": {
        "shape": true,
        "color": true,
        "position": true
      },
      "match_count": 3,
      "parse_error": false
    },
    "lexicon_size": 49,
    "cumulative_accuracy": 0.6813186813186813,
    "speaker_raw_output": "Looking at the lexicon:\n- Circle = F1\n- Yellow = G4\n- Top-right = H2\n\nThis combination \"F1-G4-H2\" is already in the lexicon as \"circle, yellow, top-right\". Perfect.\n\nF1-G4-H2",
    "listener_raw_output": "{\"shape\": \"circle\", \"color\": \"yellow\", \"position\": \"top-right\"}"
  },
  {
    "round": 92,
    "target_concept": {
      "shape": "square",
      "color": "blue",
      "position": "top-right"
    },
    "symbol_message": "F3-G2-H2",
    "decoded_concept": {
      "shape": "square",
      "color": "blue",
      "position": "top-right"
    },
    "result": {
      "success": true,
      "attribute_scores": {
        "shape": true,
        "color": true,
        "position": true
      },
      "match_count": 3,
      "parse_error": false
    },
    "lexicon_size": 50,
    "cumulative_accuracy": 0.6847826086956522,
    "speaker_raw_output": "Looking at the lexicon:\n- F3 = square\n- G2 = blue\n- H2 = top-right\n\nThis combination (F3-G2-H2) doesn't exist yet in the lexicon, but follows the established pattern perfectly.\n\nF3-G2-H2",
    "listener_raw_output": "{\"shape\": \"square\", \"color\": \"blue\", \"position\": \"top-right\"}"
  },
  {
    "round": 93,
    "target_concept": {
      "shape": "triangle",
      "color": "green",
      "position": "bottom-left"
    },
    "symbol_message": "F2-G3-H3",
    "decoded_concept": {
      "shape": "triangle",
      "color": "green",
      "position": "bottom-left"
    },
    "result": {
      "success": true,
      "attribute_scores": {
        "shape": true,
        "color": true,
        "position": true
      },
      "match_count": 3,
      "parse_error": false
    },
    "lexicon_size": 50,
    "cumulative_accuracy": 0.6881720430107527,
    "speaker_raw_output": "Looking at the lexicon:\n- F2 = triangle\n- G3 = green\n- H3 = bottom-left\n\nThis combination F2-G3-H3 is already in the lexicon as \"triangle, green, bottom-left\".\n\nF2-G3-H3",
    "listener_raw_output": "{\"shape\": \"triangle\", \"color\": \"green\", \"position\": \"bottom-left\"}"
  },
  {
    "round": 94,
    "target_concept": {
      "shape": "square",
      "color": "green",
      "position": "bottom-right"
    },
    "symbol_message": "F3-G3-H4",
    "decoded_concept": {
      "shape": "square",
      "color": "green",
      "position": "bottom-right"
    },
    "result": {
      "success": true,
      "attribute_scores": {
        "shape": true,
        "color": true,
        "position": true
      },
      "match_count": 3,
      "parse_error": false
    },
    "lexicon_size": 50,
    "cumulative_accuracy": 0.6914893617021277,
    "speaker_raw_output": "Looking at the target concept: square, green, bottom-right\n\nFrom the lexicon:\n- F3 = square\n- G3 = green\n- H4 = bottom-right\n\nThis combination F3-G3-H4 is already in the lexicon as \"square, green, bottom-right\". \n\nF3-G3-H4",
    "listener_raw_output": "{\"shape\": \"square\", \"color\": \"green\", \"position\": \"bottom-right\"}"
  },
  {
    "round": 95,
    "target_concept": {
      "shape": "star",
      "color": "blue",
      "position": "bottom-right"
    },
    "symbol_message": "F4-G2-H4",
    "decoded_concept": {
      "shape": "star",
      "color": "blue",
      "position": "bottom-right"
    },
    "result": {
      "success": true,
      "attribute_scores": {
        "shape": true,
        "color": true,
        "position": true
      },
      "match_count": 3,
      "parse_error": false
    },
    "lexicon_size": 50,
    "cumulative_accuracy": 0.6947368421052632,
    "speaker_raw_output": "Looking at the lexicon:\n- F4 = star\n- G2 = blue\n- H4 = bottom-right\n\nThis combination \"F4-G2-H4\" is already in the lexicon as \"star, blue, bottom-right\". \n\nF4-G2-H4",
    "listener_raw_output": "{\"shape\": \"star\", \"color\": \"blue\", \"position\": \"bottom-right\"}"
  },
  {
    "round": 96,
    "target_concept": {
      "shape": "triangle",
      "color": "red",
      "position": "top-left"
    },
    "symbol_message": "F2-G1-H1",
    "decoded_concept": {
      "shape": "triangle",
      "color": "red",
      "position": "top-left"
    },
    "result": {
      "success": true,
      "attribute_scores": {
        "shape": true,
        "color": true,
        "position": true
      },
      "match_count": 3,
      "parse_error": false
    },
    "lexicon_size": 50,
    "cumulative_accuracy": 0.6979166666666666,
    "speaker_raw_output": "Looking at the lexicon:\n- Triangle = F2\n- Red = G1\n- Top-left = H1\n\nThis combination exists in the lexicon as \"F2-G1-H1\" = \"triangle, red, top-left\"\n\nF2-G1-H1",
    "listener_raw_output": "{\"shape\": \"triangle\", \"color\": \"red\", \"position\": \"top-left\"}"
  },
  {
    "round": 97,
    "target_concept": {
      "shape": "triangle",
      "color": "red",
      "position": "bottom-right"
    },
    "symbol_message": "F2-G1-H4",
    "decoded_concept": {
      "shape": "triangle",
      "color": "red",
      "position": "bottom-right"
    },
    "result": {
      "success": true,
      "attribute_scores": {
        "shape": true,
        "color": true,
        "position": true
      },
      "match_count": 3,
      "parse_error": false
    },
    "lexicon_size": 50,
    "cumulative_accuracy": 0.7010309278350515,
    "speaker_raw_output": "Looking at the lexicon:\n- Triangle = F2\n- Red = G1\n- Bottom-right = H4\n\nThis combination (F2-G1-H4) already exists in the lexicon as \"triangle, red, bottom-right\". Perfect.\n\nF2-G1-H4",
    "listener_raw_output": "{\"shape\": \"triangle\", \"color\": \"red\", \"position\": \"bottom-right\"}"
  },
  {
    "round": 98,
    "target_concept": {
      "shape": "star",
      "color": "yellow",
      "position": "top-right"
    },
    "symbol_message": "F4-G4-H2",
    "decoded_concept": {
      "shape": "star",
      "color": "yellow",
      "position": "top-right"
    },
    "result": {
      "success": true,
      "attribute_scores": {
        "shape": true,
        "color": true,
        "position": true
      },
      "match_count": 3,
      "parse_error": false
    },
    "lexicon_size": 50,
    "cumulative_accuracy": 0.7040816326530612,
    "speaker_raw_output": "Looking at the lexicon:\n- F4 = star\n- G4 = yellow\n- H2 = top-right\n\nThis combination hasn't been used yet, but follows the established pattern perfectly.\n\nF4-G4-H2",
    "listener_raw_output": "{\"shape\": \"star\", \"color\": \"yellow\", \"position\": \"top-right\"}"
  },
  {
    "round": 99,
    "target_concept": {
      "shape": "star",
      "color": "red",
      "position": "bottom-right"
    },
    "symbol_message": "F4-G1-H4",
    "decoded_concept": {
      "shape": "star",
      "color": "red",
      "position": "bottom-right"
    },
    "result": {
      "success": true,
      "attribute_scores": {
        "shape": true,
        "color": true,
        "position": true
      },
      "match_count": 3,
      "parse_error": false
    },
    "lexicon_size": 50,
    "cumulative_accuracy": 0.7070707070707071,
    "speaker_raw_output": "Looking at the lexicon, I can see:\n- F4 = star\n- G1 = red\n- H4 = bottom-right\n\nAnd there's already an entry \"F4-G1-H4\": \"star, red, bottom-right\" which is exactly what I need.\n\nF4-G1-H4",
    "listener_raw_output": "{\"shape\": \"star\", \"color\": \"red\", \"position\": \"bottom-right\"}"
  },
  {
    "round": 100,
    "target_concept": {
      "shape": "triangle",
      "color": "red",
      "position": "top-left"
    },
    "symbol_message": "F2-G1-H1",
    "decoded_concept": {
      "shape": "triangle",
      "color": "red",
      "position": "top-left"
    },
    "result": {
      "success": true,
      "attribute_scores": {
        "shape": true,
        "color": true,
        "position": true
      },
      "match_count": 3,
      "parse_error": false
    },
    "lexicon_size": 50,
    "cumulative_accuracy": 0.71,
    "speaker_raw_output": "Looking at the lexicon:\n- Triangle = F2\n- Red = G1\n- Top-left = H1\n\nThis combination already exists: \"F2-G1-H1\" = \"triangle, red, top-left\" \u2713\n\nF2-G1-H1",
    "listener_raw_output": "{\"shape\": \"triangle\", \"color\": \"red\", \"position\": \"top-left\"}"
  }
]